Workbook

Sheet CI-FV
A1: PV | B1: 50000 | D1: Daniel invested $50,000 at 10% effective annual interest rate for 6 years. Calculate the future value of his investment.
A2: i | B2: 0.1
A3: n | B3: 6
A4: FV | B4: =-FV(B2,B3,,B1,0) -> 88578.05
D7: Use Excel built-in function!

Sheet Instructions
A1: Marks
A2: 2 | B2: BS
A3: 2 | B3: IS
A4: 10 | B4: BS IS
A5: 3 | B5: SCF
A6: 4 | B6: HA
A7: 4 | B7: %Change
A8: 4 | B8: VA
A9: 10 | B9: Ratio
A10: 14 | B10: CapitalBudgeting
A11: 4 | B11: TVM - CI
A12: 4 | B12: TVM - FVOA
A13: 4 | B13: TVM - PVOA
... A24: 2 | B24: Outsourcing 3
A25: =SUM(A2:A24) -> 110 | B25: Total

Sheet Cover
A1: Group # | B1: Company # | C1: Company Name | D1: Student ID | E1: First Name | F1: Family Name | G1: Contribution
A2: 8 | B2: 3 | C2: Delta | D2: 24954238 | E2: Melissa | F2: Lyon | G2: 1
A3: 8 | B3: 3 | C3: Delta | D3: 14443939 | E3: Viet Kien | F3: Nguyen | G3: 1
A4: 8 | B4: 3 | C4: Delta | D4: 24966549 | E4: Darlene | F4: Suryaputra | G4: 1
A5: 8 | B5: 3 | C5: Delta | D5: 14505578 | E5: Fabiha Tabassum | F5: Priti | G5: 1
A6: 8 | B6: 3 | C6: Delta | D6: 24445660 | E6: Kirisha | F6: Mohan | G6: 1
B9: Change only the red font to match your Group number, Student ID, First Name and Family Name. Percentage of contribution is 100% for each one if all members contributed equally, if any member contributes less, change the percentage of contribution to reflect his/ her contribution. For example, 70% percentage of contribution, this member will get 70% of the group assignment.

Sheet BS
B1: Balance sheet as at 30 June (in Million $) | H1: Balance sheet as at 30 June (in Million $)
B2: Year | C2: =SCF!C2 -> 2019 | D2: =C2+1 -> 2020 | E2: =D2+1 -> 2021 | F2: =E2+1 -> 2022 | H2: Year | I2: =VLOOKUP(H2,$B$2:$F$16,2,FALSE) -> 2019 | J2: =VLOOKUP(H2,$B$2:$F$16,3,FALSE) -> 2020 | K2: =VLOOKUP(H2,$B$2:$F$16,4,FALSE) -> 2021 | L2: =VLOOKUP(H2,$B$2:$F$16,5,FALSE) -> 2022
B3: Accounts Payable | C3: 12.5 | D3: 30 | E3: 62.5 | F3: 65 | H3: Current Assets
B4: Cash | C4: 5 | D4: 12.5 | E4: 15 | F4: 20 | H4: Cash | I4: =VLOOKUP(H4,B3:F16,2,0) -> 5 | J4: =VLOOKUP(H4,B3:F16,3,0) -> 12.5 | K4: =VLOOKUP(H4,B3:F16,4,0) -> 15 | L4: =VLOOKUP(H4,B3:F16,5,0) -> 20
B5: Notes Payable | C5: 7.5 | D5: 32.5 | E5: 20 | F5: 45 | H5: Accounts Receivable | I5: =VLOOKUP(H5,B3:F16,2,0) -> 7.5 | J5: =VLOOKUP(H5,B3:F16,3,0) -> 17.5 | K5: =VLOOKUP(H5,B3:F16,4,0) -> 20 | L5: =VLOOKUP(H5,B3:F16,5,0) -> 27.5
B6: PPE (Gross) | C6: 150 | D6: 175 | E6: 200 | F6: 225 | H6: Inventories | I6: =VLOOKUP(H6,B3:F16,2,0) -> 22.5 | J6: =VLOOKUP(H6,B3:F16,3,0) -> 33.75 | K6: =VLOOKUP(H6,B3:F16,4,0) -> 37.5 | L6: =VLOOKUP(H6,B3:F16,5,0) -> 30
B7: Long Term Loan | C7: 50 | D7: 40 | E7: 30 | F7: 20 | H7: Other Current Assets | I7: =VLOOKUP(H7,B3:F16,2,0) -> 2.5 | J7: =VLOOKUP(H7,B3:F16,3,0) -> 7.5 | K7: =VLOOKUP(H7,B3:F16,4,0) -> 8.75 | L7: =VLOOKUP(H7,B3:F16,5,0) -> 15
B8: Accounts Receivable | C8: 7.5 | D8: 17.5 | E8: 20 | F8: 27.5 | H8: Total Current Assets | I8: =SUM(I4:I7) -> 37.5 | J8: =SUM(J4:J7) -> 71.25 | K8: =SUM(K4:K7) -> 81.25 | L8: =SUM(L4:L7) -> 92.5
B9: Current Portion of LTD | C9: 10 | D9: 10 | E9: 10 | F9: 10
B10: Accumulated Depreciation | C10: 75 | D10: 83.75 | E10: 93.75 | F10: 105 | H10: Long Term Assets
B11: Inventories | C11: 22.5 | D11: 33.75 | E11: 37.5 | F11: 30 | H11: PPE (Gross) | I11: =VLOOKUP($H$11,$B$3:$F$16,2,0) -> 150 | J11: =VLOOKUP($H$11,$B$3:$F$16,3,0) -> 175 | K11: =VLOOKUP($H$11,$B$3:$F$16,4,0) -> 200 | L11: =VLOOKUP($H$11,$B$3:$F$16,5,0) -> 225
B12: Bonds Payable | C12: 15 | D12: 20 | E12: 20 | F12: 20 | H12: Accumulated Depreciation | I12: =VLOOKUP($H$12,$B$3:$F$16,2,0) -> 75 | J12: =VLOOKUP($H$12,$B$3:$F$16,3,0) -> 83.75 | K12: =VLOOKUP($H$12,$B$3:$F$16,4,0) -> 93.75 | L12: =VLOOKUP($H$12,$B$3:$F$16,5,0) -> 105
B13: Goodwill | C13: 12.5 | D13: 12.5 | E13: 12.5 | F13: 12.5 | H13: PPE (Net) | I13: =I11-I12 -> 75 | J13: =J11-J12 -> 91.25 | K13: =K11-K12 -> 106.25 | L13: =L11-L12 -> 120
B14: Contributed Capital | C14: 20 | D14: 25 | E14: 25 | F14: 30 | H14: Goodwill | I14: =VLOOKUP($H$14,$B$3:$F$16,2,0) -> 12.5 | J14: =VLOOKUP($H$14,$B$3:$F$16,3,0) -> 12.5 | K14: =VLOOKUP($H$14,$B$3:$F$16,4,0) -> 12.5 | L14: =VLOOKUP($H$14,$B$3:$F$16,5,0) -> 12.5
B15: Other Current Assets | C15: 2.5 | D15: 7.5 | E15: 8.75 | F15: 15 | H15: Total Long Term Assets | I15: =SUM(I13:I14) -> 87.5 | J15: =SUM(J13:J14) -> 103.75 | K15: =SUM(K13:K14) -> 118.75 | L15: =SUM(L13:L14) -> 132.5
B16: Retained Earnings | C16: 10 | D16: 17.5 | E16: 32.5 | F16: 35
H17: Total Assets | I17: =SUM(I8,I15) -> 125 | J17: =SUM(J8,J15) -> 175 | K17: =SUM(K8,K15) -> 200 | L17: =SUM(L8,L15) -> 225
B18: Use VLOOKUP function!
H19: Current Liabilities
H20: Accounts Payable | I20: =VLOOKUP($H$20,$B$3:$F$16,2,0) -> 12.5 | J20: =VLOOKUP($H$20,$B$3:$F$16,3,0) -> 30 | K20: =VLOOKUP($H$20,$B$3:$F$16,4,0) -> 62.5 | L20: =VLOOKUP($H$20,$B$3:$F$16,5,0) -> 65
H21: Notes Payable | I21: =VLOOKUP($H$21,$B$3:$F$16,2,0) -> 7.5 | J21: =VLOOKUP($H$21,$B$3:$F$16,3,0) -> 32.5 | K21: =VLOOKUP($H$21,$B$3:$F$16,4,0) -> 20 | L21: =VLOOKUP($H$21,$B$3:$F$16,5,0) -> 45
H22: Current Portion of LTD | I22: =VLOOKUP($H$22,$B$3:$F$16,2,0) -> 10 | J22: =VLOOKUP($H$22,$B$3:$F$16,3,0) -> 10 | K22: =VLOOKUP($H$22,$B$3:$F$16,4,0) -> 10 | L22: =VLOOKUP($H$22,$B$3:$F$16,5,0) -> 10
H23: Total Current Liabilities | I23: =SUM(I20:I22) -> 30 | J23: =SUM(J20:J22) -> 72.5 | K23: =SUM(K20:K22) -> 92.5 | L23: =SUM(L20:L22) -> 120
H25: Long Term Liabilities
H26: Long Term Loan | I26: =VLOOKUP($H$26,$B$3:$F$16,2,0) -> 50 | J26: =VLOOKUP($H$26,$B$3:$F$16,3,0) -> 40 | K26: =VLOOKUP($H$26,$B$3:$F$16,4,0) -> 30 | L26: =VLOOKUP($H$26,$B$3:$F$16,5,0) -> 20
H27: Bonds Payable | I27: =VLOOKUP($H$27,$B$3:$F$16,2,0) -> 15 | J27: =VLOOKUP($H$27,$B$3:$F$16,3,0) -> 20 | K27: =VLOOKUP($H$27,$B$3:$F$16,4,0) -> 20 | L27: =VLOOKUP($H$27,$B$3:$F$16,5,0) -> 20
H28: Total Long Term Liabilities | I28: =SUM(I26:I27) -> 65 | J28: =SUM(J26:J27) -> 60 | K28: =SUM(K26:K27) -> 50 | L28: =SUM(L26:L27) -> 40
H30: Shareholders' Equity
H31: Contributed Capital | I31: =VLOOKUP($H$31,$B$3:$F$16,2,0) -> 20 | J31: =VLOOKUP($H$31,$B$3:$F$16,3,0) -> 25 | K31: =VLOOKUP($H$31,$B$3:$F$16,4,0) -> 25 | L31: =VLOOKUP($H$31,$B$3:$F$16,5,0) -> 30
H32: Retained Earnings | I32: =VLOOKUP($H$32,$B$3:$F$16,2,0) -> 10 | J32: =VLOOKUP($H$32,$B$3:$F$16,3,0) -> 17.5 | K32: =VLOOKUP($H$32,$B$3:$F$16,4,0) -> 32.5 | L32: =VLOOKUP($H$32,$B$3:$F$16,5,0) -> 35
H33: Total Shareholders' Equity | I33: =SUM(I31:I32) -> 30 | J33: =SUM(J31:J32) -> 42.5 | K33: =SUM(K31:K32) -> 57.5 | L33: =SUM(L31:L32) -> 65
H35: Total Liabilities and Equity | I35: =SUM(I23,I28,I33) -> 125 | J35: =SUM(J23,J28,J33) -> 175 | K35: =SUM(K23,K28,K33) -> 200 | L35: =SUM(L23,L28,L33) -> 225
H37: Balance | I37: =I17-I35 -> 0 | J37: =J17-J35 -> 0 | K37: =K17-K35 -> 0 | L37: =L17-L35 -> 0

Sheet IS
B1: Income Statement for the years ended 30 June (in Million $) | H1: Income Statement for the years ended 30 June (in Million $)
B2: Year | C2: =SCF!C2 -> 2019 | D2: =C2+1 -> 2020 | E2: =D2+1 -> 2021 | F2: =E2+1 -> 2022 | H2: Year | I2: =VLOOKUP(H2,$B$2:$F$9,2,FALSE) -> 2019 | J2: =VLOOKUP(H2,$B$2:$F$9,3,FALSE) -> 2020 | K2: =VLOOKUP(H2,$B$2:$F$9,4,FALSE) -> 2021 | L2: =VLOOKUP(H2,$B$2:$F$9,5,FALSE) -> 2022
B3: Depreciation | C3: 7.5 | D3: 8.75 | E3: 10 | F3: 11.25 | H3: Sales | I3: =VLOOKUP($H$3,$B$3:$F$9,2,FALSE) -> 100 | J3: =VLOOKUP($H$3,$B$3:$F$9,3,FALSE) -> 150 | K3: =VLOOKUP($H$3,$B$3:$F$9,4,FALSE) -> 200 | L3: =VLOOKUP($H$3,$B$3:$F$9,5,FALSE) -> 250
B4: Sales | C4: 100 | D4: 150 | E4: 200 | F4: 250 | H4: Cost of Goods Sold (COGS) | I4: =VLOOKUP($H$4,$B$3:$F$9,2,0) -> 75 | J4: =VLOOKUP($H$4,$B$3:$F$9,3,0) -> 100 | K4: =VLOOKUP($H$4,$B$3:$F$9,4,0) -> 125 | L4: =VLOOKUP($H$4,$B$3:$F$9,5,0) -> 200
B5: Interest expense | C5: 7.25 | D5: 7 | E5: 6 | F5: 5 | H5: Gross Profit | I5: =I3-I4 -> 25 | J5: =J3-J4 -> 50 | K5: =K3-K4 -> 75 | L5: =L3-L4 -> 50
B6: Cost of Goods Sold (COGS) | C6: 75 | D6: 100 | E6: 125 | F6: 200 | H6: Selling, General & Administrative Expenses | I6: =VLOOKUP($H$6,$B$3:$F$9,2,0) -> 5.25 | J6: =VLOOKUP($H$6,$B$3:$F$9,3,0) -> 9.25 | K6: =VLOOKUP($H$6,$B$3:$F$9,4,0) -> 14 | L6: =VLOOKUP($H$6,$B$3:$F$9,5,0) -> 16.25
B7: Tax Rate | C7: 0.3 | D7: 0.3 | E7: 0.3 | F7: 0.3 | H7: Depreciation | I7: =VLOOKUP($H$7,$B$3:$F$9,2,0) -> 7.5 | J7: =VLOOKUP($H$7,$B$3:$F$9,3,0) -> 8.75 | K7: =VLOOKUP($H$7,$B$3:$F$9,4,0) -> 10 | L7: =VLOOKUP($H$7,$B$3:$F$9,5,0) -> 11.25
B8: Selling, General & Administrative Expenses | C8: 5.25 | D8: 9.25 | E8: 14 | F8: 16.25 | H8: Earnings Before Interest and Tax (EBIT) | I8: =I5-(I6+I7) -> 12.25 | J8: =J5-(J6+J7) -> 32 | K8: =K5-(K6+K7) -> 51 | L8: =L5-(L6+L7) -> 22.5
B9: Dividends | C9: 2.5 | D9: 10 | E9: 16.5 | F9: 9.75 | H9: Interest expense | I9: =VLOOKUP($H$9,$B$3:$F$9,2,0) -> 7.25 | J9: =VLOOKUP($H$9,$B$3:$F$9,3,0) -> 7 | K9: =VLOOKUP($H$9,$B$3:$F$9,4,0) -> 6 | L9: =VLOOKUP($H$9,$B$3:$F$9,5,0) -> 5
H10: Earnings Before Tax (EBT) | I10: =I8-I9 -> 5 | J10: =J8-J9 -> 25 | K10: =K8-K9 -> 45 | L10: =L8-L9 -> 17.5
B11: Use VLOOKUP function! | G11: 0.3 | H11: Tax Rate | I11: =VLOOKUP($H$11,$B$3:$F$9,2,0) -> 0.3 | J11: =VLOOKUP($H$11,$B$3:$F$9,3,0) -> 0.3 | K11: =VLOOKUP($H$11,$B$3:$F$9,4,0) -> 0.3 | L11: =VLOOKUP($H$11,$B$3:$F$9,5,0) -> 0.3
H12: Tax expense | I12: =I10*I11 -> 1.5 | J12: =J10*J11 -> 7.5 | K12: =K10*K11 -> 13.5 | L12: =L10*L11 -> 5.25
H13: Net Income (NI) | I13: =I10-I12 -> 3.5 | J13: =J10-J12 -> 17.5 | K13: =K10-K12 -> 31.5 | L13: =L10-L12 -> 12.25
H14: Dividends | I14: =VLOOKUP($H$14,$B$3:$F$9,2,0) -> 2.5 | J14: =VLOOKUP($H$14,$B$3:$F$9,3,0) -> 10 | K14: =VLOOKUP($H$14,$B$3:$F$9,4,0) -> 16.5 | L14: =VLOOKUP($H$14,$B$3:$F$9,5,0) -> 9.75
H15: Additional Retained Earnings (in million $) | I15: =I13-I14 -> 1 | J15: =J13-J14 -> 7.5 | K15: =K13-K14 -> 15 | L15: =L13-L14 -> 2.5

Sheet BS IS
A1: Balance sheet as at 30 June (in Million $) | E1: Income Statement for the years ended 30 June (in Million $) | H1: Financial Ratio and Assumptions
B2: =SCF!E2 -> 2021 | C2: =B2+1 -> 2022 | F2: =C2 -> 2022
A3: Cash | B3: 128 | C3: =C13*I7 -> 192 | E3: Sales | F3: =(365/I9)*200 -> 888.88889 | H3: Long-term debt ratio | I3: 0.8045977
A4: Account receivables | B4: 160 | C4: =C6-C5-C3 -> 200 | E4: Cost of Goods Sold (COGS) | F4: =C5*I8 -> 569.49153 | H4: Times interest earned | I4: 3
A5: Inventory | B5: 192 | C5: =C6-(I6*C13) -> 280 | E5: Selling, General & Administrative Expenses | F5: 48 | H5: Current ratio | I5: 1.826087
A6: Total Current Assets | B6: 480 | C6: =C13*I5-D8 -> 672 | E6: Depreciation | F6: 32 | H6: Quick ratio | I6: 1.0652174
A7: PPE(Net) | B7: 1120 | C7: =C16-C6 -> 1088 | E7: Earnings Before Interest and Tax (EBIT) | F7: =(F3-F4)-F5-F6 -> 239.39736 | H7: Cash ratio | I7: 0.52173913
A8: Total Assets | B8: 1600 | C8: =SUM(C6:C7) -> 1760 | E8: Interest expense | F8: =F7/I4 -> 79.799121 | H8: Inventory turnover | I8: 2.0338983
E9: Earnings Before Tax (EBT) | F9: =F7-F8 -> 159.59824 | H9: Days’ Sales in Receivables (days) | I9: 82.125
A10: Accounts Payable | B10: 32 | C10: 128 | E10: Tax expense | F10: =F9*I10 -> 47.879473 | H10: Tax rate | I10: 0.3
A11: Notes Payable | B11: 48 | C11: 160 | E11: Net Income (NI) | F11: =F9-F10 -> 111.71877
A12: Current Portion of LTD | B12: 80 | C12: 80
A13: Total Current Liabilities | B13: 160 | C13: =SUM(C10:C12) -> 368
A14: Long-term-debt | B14: 1200 | C14: =(I3*C15)/(1-I3) -> 1251.7647
A15: Equity | B15: 240 | C15: =C6-C13 -> 304
A16: Total Liabilities & Equity | B16: 1600 | C16: 1760

Sheet SCF
B1: Income Statement for the years ended 30 June (in Million $) | I1: Statement of Cash Flows for the years ended 30 June (in Million $)
C2: 2019 | D2: =C2+1 -> 2020 | E2: =D2+1 -> 2021 | F2: =E2+1 -> 2022 | J2: =C2 -> 2019 | K2: =D2 -> 2020 | L2: =E2 -> 2021 | M2: =F2 -> 2022
B3: Sales | C3: 50 | D3: 75 | E3: 100 | F3: 125 | I3: Cash Flow from Operation
B4: Cost of Goods Sold (COGS) | C4: 37.5 | D4: 50 | E4: 62.5 | F4: 100 | I4: =B12 -> Net Income (NI) | J4: =VLOOKUP($I$4,$B$3:$F$17,2,0) -> 1.75 | K4: =VLOOKUP($I$4,$B$3:$F$17,3,0) -> 8.75 | L4: =VLOOKUP($I$4,$B$3:$F$17,4,0) -> 15.75 | M4: =VLOOKUP($I$4,$B$3:$F$17,5,0) -> 6.125
B5: Gross Profit | C5: =C3-C4 -> 12.5 | D5: =D3-D4 -> 25 | E5: =E3-E4 -> 37.5 | F5: =F3-F4 -> 25 | I5: =B7 -> Depreciation | J5: =VLOOKUP($I$5,$B$3:$F$17,2,0) -> 3.75 | K5: =VLOOKUP($I$5,$B$3:$F$17,3,0) -> 4.375 | L5: =VLOOKUP($I$5,$B$3:$F$17,4,0) -> 5 | M5: =VLOOKUP($I$5,$B$3:$F$17,5,0) -> 5.625
B6: Selling, General & Administrative Expenses | C6: 2.625 | D6: 4.625 | E6: 7 | F6: 8.125 | H6: Δ | I6: =B23 -> Accounts Receivable | J6: 0 | K6: =-C23-D23 -> -12.5 | L6: =-E23-D23 -> -18.75 | M6: =-F23-E23 -> -23.75 | N6: -
B7: Depreciation | C7: 3.75 | D7: 4.375 | E7: 5 | F7: 5.625 | H7: Δ | I7: =B24 -> Inventories | J7: 0 | K7: =-D24-C24 -> -28.125 | L7: =-E24-D24 -> -35.625 | M7: =-F24-E24 -> -33.75 | N7: -
B8: Earnings Before Interest and Tax (EBIT) | C8: =C5-SUM(C6:C7) -> 6.125 | D8: =D5-SUM(D6:D7) -> 16 | E8: =E5-SUM(E6:E7) -> 25.5 | F8: =F5-SUM(F6:F7) -> 11.25 | H8: Δ | I8: =B25 -> Other Current Assets | J8: 0 | K8: =D25-C25 -> 2.5 | L8: =E25-D25 -> 0.625 | M8: =F25-E25 -> 3.125 | N8: +
B9: Interest expense | C9: 3.625 | D9: 3.5 | E9: 3 | F9: 2.5 | H9: Δ | I9: =B38 -> Accounts Payable | J9: 0 | K9: =D38-C38 -> 8.75 | L9: =E38-D38 -> 16.25 | M9: =F38-E38 -> 1.25 | N9: +
B10: Earnings Before Tax (EBT) | C10: =C8-C9 -> 2.5 | D10: =D8-D9 -> 12.5 | E10: =E8-E9 -> 22.5 | F10: =F8-F9 -> 8.75 | I10: Net Cash Flow from Operation | J10: =SUM(J4:J9) -> 5.5 | K10: =SUM(K4:K9) -> -16.25 | L10: =SUM(L4:L9) -> -16.75 | M10: =SUM(M4:M9) -> -41.375
A11: 0.3 | B11: Tax expense | C11: =C10*$A$11 -> 0.75 | D11: =D10*$A$11 -> 3.75 | E11: =E10*$A$11 -> 6.75 | F11: =F10*$A$11 -> 2.625
B12: Net Income (NI) | C12: =C10-C11 -> 1.75 | D12: =D10-D11 -> 8.75 | E12: =E10-E11 -> 15.75 | F12: =F10-F11 -> 6.125 | I12: Cash Flow from Investing
B13: Dividends (in million $) | C13: 1.25 | D13: 5 | E13: 8.25 | F13: 4.875 | H13: Δ | I13: =B31 -> PPE (Net) | J13: 0 | K13: =-D31-C31 -> -83.125 | L13: =-E31-D31 -> -98.75 | M13: =-F31-E31 -> -113.125 | N13: -
B14: Additional Retained Earnings (in million $) | C14: =C12-C13 -> 0.5 | D14: =D12-D13 -> 3.75 | E14: =E12-E13 -> 7.5 | F14: =F12-F13 -> 1.25 | H14: Δ | I14: =B32 -> Goodwill | J14: 0 | K14: =-D32-C32 -> -12.5 | L14: =-E32-D32 -> -12.5 | M14: =-F32-E32 -> -12.5 | N14: -
I15: Net Cash Flow from Investing | J15: =SUM(J13:J14) -> 0 | K15: =SUM(K13:K14) -> -95.625 | L15: =SUM(L13:L14) -> -111.25 | M15: =SUM(M13:M14) -> -125.625
B16: Shares Outstanding (in million) | C16: 25 | D16: 25 | E16: 25 | F16: 25
B17: Market Value per Share ($/Share) | C17: 5 | D17: 7.5 | E17: 8.75 | F17: 6.25 | I17: Cash Flow from Financing
I18: =B13 -> Dividends (in million $) | J18: =VLOOKUP(I18,B3:F17,2,0) -> 1.25 | K18: =VLOOKUP(I18,B3:F17,3,FALSE) -> 5 | L18: =VLOOKUP(I18,B3:F17,4,FALSE) -> 8.25 | M18: =VLOOKUP(I18,B3:F17,4,FALSE) -> 8.25
B19: Balance sheet as at 30 June (in Million $) | H19: Δ | I19: =B39 -> Notes Payable | J19: 0 | K19: =D39-C39 -> 12.5 | L19: =E39-D39 -> -6.25 | M19: =F39-E39 -> 12.5 | N19: +
C20: =C2 -> 2019 | D20: =D2 -> 2020 | E20: =E2 -> 2021 | F20: =F2 -> 2022 | H20: Δ | I20: =B40 -> Current Portion of LTD | J20: 0 | K20: =D40-C40 -> 0 | L20: =E40-D40 -> 0 | M20: =F40-E40 -> 0 | N20: +
B21: Current Assets | H21: Δ | I21: =B44 -> Long Term Loan | J21: 0 | K21: =D44-C44 -> -5 | L21: =E44-D44 -> -5 | M21: =F44-E44 -> -5 | N21: +
B22: Cash | C22: 2.5 | D22: 6.25 | E22: 7.5 | F22: 10 | H22: Δ | I22: =B45 -> Bonds Payable | J22: 0 | K22: =D45-C45 -> 2.5 | L22: =E45-D45 -> 0 | M22: =F45-E45 -> 0 | N22: +
B23: Accounts Receivable | C23: 3.75 | D23: 8.75 | E23: 10 | F23: 13.75 | H23: Δ | I23: =B49 -> Contributed Capital | J23: 0 | K23: =D49-C49 -> 2.5 | L23: =E49-D49 -> 0 | M23: =F49-E49 -> 2.5 | N23: +
B24: Inventories | C24: 11.25 | D24: 16.875 | E24: 18.75 | F24: 15 | I24: Net Cash Flow from Financing | J24: =SUM(J18:J23) -> 1.25 | K24: =SUM(K18:K23) -> 17.5 | L24: =SUM(L18:L23) -> -3 | M24: =SUM(M18:M23) -> 18.25
B25: Other Current Assets | C25: 1.25 | D25: 3.75 | E25: 4.375 | F25: 7.5
B26: Total Current Assets | C26: =SUM(C22:C25) -> 18.75 | D26: =SUM(D22:D25) -> 35.625 | E26: =SUM(E22:E25) -> 40.625 | F26: =SUM(F22:F25) -> 46.25 | I26: Net Cash Flow | J26: =SUM(J10,J15,J24) -> 6.75 | K26: =SUM(K10,K15,K24) -> -94.375 | L26: =SUM(L10,L15,L24) -> -131 | M26: =SUM(M10,M15,M24) -> -148.75
B28: Long Term Assets | I28: Beginning Cash | J28: =C22 -> 2.5 | K28: =D22 -> 6.25 | L28: =E22 -> 7.5 | M28: =F22 -> 10
B29: PPE (Gross) | C29: 75 | D29: 87.5 | E29: 100 | F29: 112.5 | I29: Ending Cash | J29: =SUM(J26,J28) -> 9.25 | K29: =SUM(K26,K28) -> -88.125 | L29: =SUM(L26,L28) -> -123.5 | M29: =SUM(M26,M28) -> -138.75
B30: Acc Dep | C30: 37.5 | D30: =C30+D7 -> 41.875 | E30: =D30+E7 -> 46.875 | F30: =E30+F7 -> 52.5
B31: PPE (Net) | C31: =C29-C30 -> 37.5 | D31: =D29-D30 -> 45.625 | E31: =E29-E30 -> 53.125 | F31: =F29-F30 -> 60
B32: Goodwill | C32: 6.25 | D32: 6.25 | E32: 6.25 | F32: 6.25
B33: Total Long Term Assets | C33: =SUM(C31:C32) -> 43.75 | D33: =SUM(D31:D32) -> 51.875 | E33: =SUM(E31:E32) -> 59.375 | F33: =SUM(F31:F32) -> 66.25
B35: Total Assets | C35: =C26+C33 -> 62.5 | D35: =D26+D33 -> 87.5 | E35: =E26+E33 -> 100 | F35: =F26+F33 -> 112.5
B37: Current Liabilities
B38: Accounts Payable | C38: 6.25 | D38: 15 | E38: 31.25 | F38: 32.5
B39: Notes Payable | C39: 3.75 | D39: 16.25 | E39: 10 | F39: 22.5
B40: Current Portion of LTD | C40: 5 | D40: =C40 -> 5 | E40: =D40 -> 5 | F40: =E40 -> 5
B41: Total Current Liabilities | C41: =SUM(C38:C40) -> 15 | D41: =SUM(D38:D40) -> 36.25 | E41: =SUM(E38:E40) -> 46.25 | F41: =SUM(F38:F40) -> 60
B43: Long Term Liabilities
B44: Long Term Loan | C44: 25 | D44: =C44-D40 -> 20 | E44: =D44-E40 -> 15 | F44: =E44-F40 -> 10
B45: Bonds Payable | C45: 7.5 | D45: 10 | E45: 10 | F45: 10
B46: Total Long Term Liabilities | C46: =SUM(C44:C45) -> 32.5 | D46: =SUM(D44:D45) -> 30 | E46: =SUM(E44:E45) -> 25 | F46: =SUM(F44:F45) -> 20
B48: Shareholders' Equity
B49: Contributed Capital | C49: 10 | D49: 12.5 | E49: 12.5 | F49: 15
B50: Retained Earnings | C50: 5 | D50: =C50+D14 -> 8.75 | E50: =D50+E14 -> 16.25 | F50: =E50+F14 -> 17.5
B51: Total Shareholders' Equity | C51: =SUM(C49:C50) -> 15 | D51: =SUM(D49:D50) -> 21.25 | E51: =SUM(E49:E50) -> 28.75 | F51: =SUM(F49:F50) -> 32.5
B53: Total Liabilities and Equity | C53: =C41+C46+C51 -> 62.5 | D53: =D41+D46+D51 -> 87.5 | E53: =E41+E46+E51 -> 100 | F53: =F41+F46+F51 -> 112.5
B55: Balance | C55: =C35-C53 -> 0 | D55: =D35-D53 -> 0 | E55: =E35-E53 -> 0 | F55: =F35-F53 -> 0

Sheet HA
B1: Income Statement for the years ended 30 June (in Million $) | H1: Horizontal Analysis
C2: =SCF!C2 -> 2019 | D2: =SCF!D2 -> 2020 | E2: =SCF!E2 -> 2021 | F2: =SCF!F2 -> 2022 | I2: =C2 -> 2019 | J2: =D2 -> 2020 | K2: =E2 -> 2021 | L2: =F2 -> 2022
B3: =SCF!B3 -> Sales | C3: =SCF!C3 -> 50 | D3: =SCF!D3 -> 75 | E3: =SCF!E3 -> 100 | F3: =SCF!F3 -> 125 | H3: =B3 -> Sales | I3: 0 | J3: =(D3-$C$3)/$C$3 -> 0.5 | K3: =(E3-$C$3)/$C$3 -> 1 | L3: =(F3-$C$3)/$C$3 -> 1.5
B4: =SCF!B4 -> Cost of Goods Sold (COGS) | C4: =SCF!C4 -> 37.5 | D4: =SCF!D4 -> 50 | E4: =SCF!E4 -> 62.5 | F4: =SCF!F4 -> 100 | H4: =B4 -> Cost of Goods Sold (COGS) | I4: 0 | J4: =(D4-$C$4)/$C$4 -> 0.33333333 | K4: =(E4-$C$4)/$C$4 -> 0.66666667 | L4: =(F4-$C$4)/$C$4 -> 1.6666667
B5: =SCF!B5 -> Gross Profit | C5: =C3-C4 -> 12.5 | D5: =D3-D4 -> 25 | E5: =E3-E4 -> 37.5 | F5: =F3-F4 -> 25 | H5: =B5 -> Gross Profit | I5: 0 | J5: =(D5-$C$5)/$C$5 -> 1 | K5: =(E5-$C$5)/$C$5 -> 2 | L5: =(F5-$C$5)/$C$5 -> 1
B6: =SCF!B6 -> Selling, General & Administrative Expenses | C6: =SCF!C6 -> 2.625 | D6: =SCF!D6 -> 4.625 | E6: =SCF!E6 -> 7 | F6: =SCF!F6 -> 8.125 | H6: =B6 -> Selling, General & Administrative Expenses | I6: 0 | J6: =(D6-$C$6)/$C$6 -> 0.76190476 | K6: =(E6-$C$6)/$C$6 -> 1.6666667 | L6: =(F6-$C$6)/$C$6 -> 2.0952381
B7: =SCF!B7 -> Depreciation | C7: =SCF!C7 -> 3.75 | D7: =SCF!D7 -> 4.375 | E7: =SCF!E7 -> 5 | F7: =SCF!F7 -> 5.625 | H7: =B7 -> Depreciation | I7: 0 | J7: =(D7-$C$7)/$C$7 -> 0.16666667 | K7: =(E7-$C$7)/$C$7 -> 0.33333333 | L7: =(F7-$C$7)/$C$7 -> 0.5
B8: =SCF!B8 -> Earnings Before Interest and Tax (EBIT) | C8: =C5-SUM(C6:C7) -> 6.125 | D8: =D5-SUM(D6:D7) -> 16 | E8: =E5-SUM(E6:E7) -> 25.5 | F8: =F5-SUM(F6:F7) -> 11.25 | H8: =B8 -> Earnings Before Interest and Tax (EBIT) | I8: 0 | J8: =(D8-$C$8)/$C$8 -> 1.6122449 | K8: =(E8-$C$8)/$C$8 -> 3.1632653 | L8: =(F8-$C$8)/$C$8 -> 0.83673469
B9: =SCF!B9 -> Interest expense | C9: =SCF!C9 -> 3.625 | D9: =SCF!D9 -> 3.5 | E9: =SCF!E9 -> 3 | F9: =SCF!F9 -> 2.5 | H9: =B9 -> Interest expense | I9: 0 | J9: =(D9-$C$9)/$C$9 -> -0.034482759 | K9: =(E9-$C$9)/$C$9 -> -0.17241379 | L9: =(F9-$C$9)/$C$9 -> -0.31034483
B10: =SCF!B10 -> Earnings Before Tax (EBT) | C10: =C8-C9 -> 2.5 | D10: =D8-D9 -> 12.5 | E10: =E8-E9 -> 22.5 | F10: =F8-F9 -> 8.75 | H10: =B10 -> Earnings Before Tax (EBT) | I10: 0 | J10: =(D10-$C$10)/$C$10 -> 4 | K10: =(E10-$C$10)/$C$10 -> 8 | L10: =(F10-$C$10)/$C$10 -> 2.5
A11: =SCF!A11 -> 0.3 | B11: =SCF!B11 -> Tax expense | C11: =C10*$A$11 -> 0.75 | D11: =D10*$A$11 -> 3.75 | E11: =E10*$A$11 -> 6.75 | F11: =F10*$A$11 -> 2.625 | H11: =B11 -> Tax expense | I11: 0 | J11: =(D11-$C$11)/$C$11 -> 4 | K11: =(E11-$C$11)/$C$11 -> 8 | L11: =(F11-$C$11)/$C$11 -> 2.5
B12: =SCF!B12 -> Net Income (NI) | C12: =C10-C11 -> 1.75 | D12: =D10-D11 -> 8.75 | E12: =E10-E11 -> 15.75 | F12: =F10-F11 -> 6.125 | H12: =B12 -> Net Income (NI) | I12: 0 | J12: =(D12-$C$12)/$C$12 -> 4 | K12: =(E12-$C$12)/$C$12 -> 8 | L12: =(F12-$C$12)/$C$12 -> 2.5
B13: =SCF!B13 -> Dividends (in million $) | C13: =SCF!C13 -> 1.25 | D13: =SCF!D13 -> 5 | E13: =SCF!E13 -> 8.25 | F13: =SCF!F13 -> 4.875
B14: =SCF!B14 -> Additional Retained Earnings (in million $) | C14: =C12-C13 -> 0.5 | D14: =D12-D13 -> 3.75 | E14: =E12-E13 -> 7.5 | F14: =F12-F13 -> 1.25
B16: =SCF!B16 -> Shares Outstanding (in million) | C16: =SCF!C16 -> 25 | D16: =SCF!D16 -> 25 | E16: =SCF!E16 -> 25 | F16: =SCF!F16 -> 25
B17: =SCF!B17 -> Market Value per Share ($/Share) | C17: =SCF!C17 -> 5 | D17: =SCF!D17 -> 7.5 | E17: =SCF!E17 -> 8.75 | F17: =SCF!F17 -> 6.25
B19: Balance sheet as at 30 June (in Million $) | H19: Horizontal Analysis
C20: =C2 -> 2019 | D20: =D2 -> 2020 | E20: =E2 -> 2021 | F20: =F2 -> 2022 | I20: =C20 -> 2019 | J20: =D20 -> 2020 | K20: =E20 -> 2021 | L20: =F20 -> 2022
B21: =SCF!B21 -> Current Assets | H21: =B21 -> Current Assets
B22: =SCF!B22 -> Cash | C22: =SCF!C22 -> 2.5 | D22: =SCF!D22 -> 6.25 | E22: =SCF!E22 -> 7.5 | F22: =SCF!F22 -> 10 | H22: =B22 -> Cash | I22: 0 | J22: =(D22-$C$22)/$C$22 -> 1.5 | K22: =(E22-$C$22)/$C$22 -> 2 | L22: =(F22-$C$22)/$C$22 -> 3
B23: =SCF!B23 -> Accounts Receivable | C23: =SCF!C23 -> 3.75 | D23: =SCF!D23 -> 8.75 | E23: =SCF!E23 -> 10 | F23: =SCF!F23 -> 13.75 | H23: =B23 -> Accounts Receivable | I23: 0 | J23: =(D23-$C$23)/$C$23 -> 1.3333333 | K23: =(E23-$C$23)/$C$23 -> 1.6666667 | L23: =(F23-$C$23)/$C$23 -> 2.6666667
B24: =SCF!B24 -> Inventories | C24: =SCF!C24 -> 11.25 | D24: =SCF!D24 -> 16.875 | E24: =SCF!E24 -> 18.75 | F24: =SCF!F24 -> 15 | H24: =B24 -> Inventories | I24: 0 | J24: =(D24-$C$24)/$C$24 -> 0.5 | K24: =(E24-$C$24)/$C$24 -> 0.66666667 | L24: =(F24-$C$24)/$C$24 -> 0.33333333
B25: =SCF!B25 -> Other Current Assets | C25: =SCF!C25 -> 1.25 | D25: =SCF!D25 -> 3.75 | E25: =SCF!E25 -> 4.375 | F25: =SCF!F25 -> 7.5 | H25: =B25 -> Other Current Assets | I25: 0 | J25: =(D25-$C$25)/$C$25 -> 2 | K25: =(E25-$C$25)/$C$25 -> 2.5 | L25: =(F25-$C$25)/$C$25 -> 5
B26: =SCF!B26 -> Total Current Assets | C26: =SUM(C22:C25) -> 18.75 | D26: =SUM(D22:D25) -> 35.625 | E26: =SUM(E22:E25) -> 40.625 | F26: =SUM(F22:F25) -> 46.25 | H26: =B26 -> Total Current Assets | I26: 0 | J26: =(D26-$C$26)/$C$26 -> 0.9 | K26: =(E26-$C$26)/$C$26 -> 1.1666667 | L26: =(F26-$C$26)/$C$26 -> 1.4666667
B28: =SCF!B28 -> Long Term Assets | H28: =B28 -> Long Term Assets
B29: =SCF!B29 -> PPE (Gross) | C29: =SCF!C29 -> 75 | D29: =SCF!D29 -> 87.5 | E29: =SCF!E29 -> 100 | F29: =SCF!F29 -> 112.5 | H29: =B29 -> PPE (Gross) | I29: 0 | J29: =(D29-$C$29)/$C$29 -> 0.16666667 | K29: =(E29-$C$29)/$C$29 -> 0.33333333 | L29: =(F29-$C$29)/$C$29 -> 0.5
B30: =SCF!B30 -> Acc Dep | C30: =SCF!C30 -> 37.5 | D30: =SCF!D30 -> 41.875 | E30: =SCF!E30 -> 46.875 | F30: =SCF!F30 -> 52.5 | H30: =B30 -> Acc Dep | I30: 0 | J30: =(D30-$C$30)/$C$30 -> 0.11666667 | K30: =(E30-$C$30)/$C$30 -> 0.25 | L30: =(F30-$C$30)/$C$30 -> 0.4
B31: =SCF!B31 -> PPE (Net) | C31: =C29-C30 -> 37.5 | D31: =D29-D30 -> 45.625 | E31: =E29-E30 -> 53.125 | F31: =F29-F30 -> 60 | H31: =B31 -> PPE (Net) | I31: 0 | J31: =(D31-$C$31)/$C$31 -> 0.21666667 | K31: =(E31-$C$31)/$C$31 -> 0.41666667 | L31: =(F31-$C$31)/$C$31 -> 0.6
B32: =SCF!B32 -> Goodwill | C32: =SCF!C32 -> 6.25 | D32: =SCF!D32 -> 6.25 | E32: =SCF!E32 -> 6.25 | F32: =SCF!F32 -> 6.25 | H32: =B32 -> Goodwill | I32: 0 | J32: =(D32-$C$32)/$C$32 -> 0 | K32: =(E32-$C$32)/$C$32 -> 0 | L32: =(F32-$C$32)/$C$32 -> 0
B33: =SCF!B33 -> Total Long Term Assets | C33: =SUM(C31:C32) -> 43.75 | D33: =SUM(D31:D32) -> 51.875 | E33: =SUM(E31:E32) -> 59.375 | F33: =SUM(F31:F32) -> 66.25 | H33: =B33 -> Total Long Term Assets | I33: 0 | J33: =(D33-$C$33)/$C$33 -> 0.18571429 | K33: =(E33-$C$33)/$C$33 -> 0.35714286 | L33: =(F33-$C$33)/$C$33 -> 0.51428571
B35: =SCF!B35 -> Total Assets | C35: =C26+C33 -> 62.5 | D35: =D26+D33 -> 87.5 | E35: =E26+E33 -> 100 | F35: =F26+F33 -> 112.5 | H35: =B35 -> Total Assets | I35: 0 | J35: =(D35-$C$35)/$C$35 -> 0.4 | K35: =(E35-$C$35)/$C$35 -> 0.6 | L35: =(F35-$C$35)/$C$35 -> 0.8
B37: =SCF!B37 -> Current Liabilities | H37: =B37 -> Current Liabilities
B38: =SCF!B38 -> Accounts Payable | C38: =SCF!C38 -> 6.25 | D38: =SCF!D38 -> 15 | E38: =SCF!E38 -> 31.25 | F38: =SCF!F38 -> 32.5 | H38: =B38 -> Accounts Payable | I38: 0 | J38: =(D38-$C$38)/$C$38 -> 1.4 | K38: =(E38-$C$38)/$C$38 -> 4 | L38: =(F38-$C$38)/$C$38 -> 4.2
B39: =SCF!B39 -> Notes Payable | C39: =SCF!C39 -> 3.75 | D39: =SCF!D39 -> 16.25 | E39: =SCF!E39 -> 10 | F39: =SCF!F39 -> 22.5 | H39: =B39 -> Notes Payable | I39: 0 | J39: =(D39-$C$39)/$C$39 -> 3.3333333 | K39: =(E39-$C$39)/$C$39 -> 1.6666667 | L39: =(F39-$C$39)/$C$39 -> 5
B40: =SCF!B40 -> Current Portion of LTD | C40: =SCF!C40 -> 5 | D40: =SCF!D40 -> 5 | E40: =SCF!E40 -> 5 | F40: =SCF!F40 -> 5 | H40: =B40 -> Current Portion of LTD | I40: 0 | J40: =(D40-$C$40)/$C$40 -> 0 | K40: =(E40-$C$40)/$C$40 -> 0 | L40: =(F40-$C$40)/$C$40 -> 0
B41: =SCF!B41 -> Total Current Liabilities | C41: =SUM(C38:C40) -> 15 | D41: =SUM(D38:D40) -> 36.25 | E41: =SUM(E38:E40) -> 46.25 | F41: =SUM(F38:F40) -> 60 | H41: =B41 -> Total Current Liabilities | I41: 0 | J41: =(D41-$C$41)/$C$41 -> 1.4166667 | K41: =(E41-$C$41)/$C$41 -> 2.0833333 | L41: =(F41-$C$41)/$C$41 -> 3
B43: =SCF!B43 -> Long Term Liabilities | H43: =B43 -> Long Term Liabilities
B44: =SCF!B44 -> Long Term Loan | C44: =SCF!C44 -> 25 | D44: =SCF!D44 -> 20 | E44: =SCF!E44 -> 15 | F44: =SCF!F44 -> 10 | H44: =B44 -> Long Term Loan | I44: 0 | J44: =(D44-$C$44)/$C$44 -> -0.2 | K44: =(E44-$C$44)/$C$44 -> -0.4 | L44: =(F44-$C$44)/$C$44 -> -0.6
B45: =SCF!B45 -> Bonds Payable | C45: =SCF!C45 -> 7.5 | D45: =SCF!D45 -> 10 | E45: =SCF!E45 -> 10 | F45: =SCF!F45 -> 10 | H45: =B45 -> Bonds Payable | I45: 0 | J45: =(D45-$C$45)/$C$45 -> 0.33333333 | K45: =(E45-$C$45)/$C$45 -> 0.33333333 | L45: =(F45-$C$45)/$C$45 -> 0.33333333
B46: =SCF!B46 -> Total Long Term Liabilities | C46: =SUM(C44:C45) -> 32.5 | D46: =SUM(D44:D45) -> 30 | E46: =SUM(E44:E45) -> 25 | F46: =SUM(F44:F45) -> 20 | H46: =B46 -> Total Long Term Liabilities | I46: 0 | J46: =(D46-$C$46)/$C$46 -> -0.076923077 | K46: =(E46-$C$46)/$C$46 -> -0.23076923 | L46: =(F46-$C$46)/$C$46 -> -0.38461538
B48: =SCF!B48 -> Shareholders' Equity | H48: =B48 -> Shareholders' Equity
B49: =SCF!B49 -> Contributed Capital | C49: =SCF!C49 -> 10 | D49: =SCF!D49 -> 12.5 | E49: =SCF!E49 -> 12.5 | F49: =SCF!F49 -> 15 | H49: =B49 -> Contributed Capital | I49: 0 | J49: =(D49-$C$49)/$C$49 -> 0.25 | K49: =(E49-$C$49)/$C$49 -> 0.25 | L49: =(F49-$C$49)/$C$49 -> 0.5
B50: =SCF!B50 -> Retained Earnings | C50: =SCF!C50 -> 5 | D50: =C50+D14 -> 8.75 | E50: =D50+E14 -> 16.25 | F50: =E50+F14 -> 17.5 | H50: =B50 -> Retained Earnings | I50: 0 | J50: =(D50-$C$50)/$C$50 -> 0.75 | K50: =(E50-$C$50)/$C$50 -> 2.25 | L50: =(F50-$C$50)/$C$50 -> 2.5
B51: =SCF!B51 -> Total Shareholders' Equity | C51: =SUM(C49:C50) -> 15 | D51: =SUM(D49:D50) -> 21.25 | E51: =SUM(E49:E50) -> 28.75 | F51: =SUM(F49:F50) -> 32.5 | H51: =B51 -> Total Shareholders' Equity | I51: 0 | J51: =(D51-$C$51)/$C$51 -> 0.41666667 | K51: =(E51-$C$51)/$C$51 -> 0.91666667 | L51: =(F51-$C$51)/$C$51 -> 1.1666667
B53: =SCF!B53 -> Total Liabilities and Equity | C53: =C41+C46+C51 -> 62.5 | D53: =D41+D46+D51 -> 87.5 | E53: =E41+E46+E51 -> 100 | F53: =F41+F46+F51 -> 112.5 | H53: =B53 -> Total Liabilities and Equity | I53: 0 | J53: =(D53-$C$53)/$C$53 -> 0.4 | K53: =(E53-$C$53)/$C$53 -> 0.6 | L53: =(F53-$C$53)/$C$53 -> 0.8
B55: =SCF!B55 -> Balance | C55: =C35-C53 -> 0 | D55: =D35-D53 -> 0 | E55: =E35-E53 -> 0 | F55: =F35-F53 -> 0

Sheet %Change
B1: Income Statement for the years ended 30 June (in Million $) | H1: Percentage Change (yoy)
C2: =SCF!C2 -> 2019 | D2: =SCF!D2 -> 2020 | E2: =SCF!E2 -> 2021 | F2: =SCF!F2 -> 2022 | I2: =C2 -> 2019 | J2: =D2 -> 2020 | K2: =E2 -> 2021 | L2: =F2 -> 2022
B3: =SCF!B3 -> Sales | C3: =SCF!C3 -> 50 | D3: =SCF!D3 -> 75 | E3: =SCF!E3 -> 100 | F3: =SCF!F3 -> 125 | H3: =B3 -> Sales | I3: 0 | J3: =(D3-C3)/C3 -> 0.5 | K3: =(E3-D3)/D3 -> 0.33333333 | L3: =(F3-E3)/E3 -> 0.25
B4: =SCF!B4 -> Cost of Goods Sold (COGS) | C4: =SCF!C4 -> 37.5 | D4: =SCF!D4 -> 50 | E4: =SCF!E4 -> 62.5 | F4: =SCF!F4 -> 100 | H4: =B4 -> Cost of Goods Sold (COGS) | I4: 0 | J4: =(D4-C4)/C4 -> 0.33333333 | K4: =(E4-D4)/D4 -> 0.25 | L4: =(F4-E4)/E4 -> 0.6
B5: =SCF!B5 -> Gross Profit | C5: =C3-C4 -> 12.5 | D5: =D3-D4 -> 25 | E5: =E3-E4 -> 37.5 | F5: =F3-F4 -> 25 | H5: =B5 -> Gross Profit | I5: 0 | J5: =(D5-C5)/C5 -> 1 | K5: =(E5-D5)/D5 -> 0.5 | L5: =(F5-E5)/E5 -> -0.33333333
B6: =SCF!B6 -> Selling, General & Administrative Expenses | C6: =SCF!C6 -> 2.625 | D6: =SCF!D6 -> 4.625 | E6: =SCF!E6 -> 7 | F6: =SCF!F6 -> 8.125 | H6: =B6 -> Selling, General & Administrative Expenses | I6: 0 | J6: =(D6-C6)/C6 -> 0.76190476 | K6: =(E6-D6)/D6 -> 0.51351351 | L6: =(F6-E6)/E6 -> 0.16071429
B7: =SCF!B7 -> Depreciation | C7: =SCF!C7 -> 3.75 | D7: =SCF!D7 -> 4.375 | E7: =SCF!E7 -> 5 | F7: =SCF!F7 -> 5.625 | H7: =B7 -> Depreciation | I7: 0 | J7: =(D7-C7)/C7 -> 0.16666667 | K7: =(E7-D7)/D7 -> 0.14285714 | L7: =(F7-E7)/E7 -> 0.125
B8: =SCF!B8 -> Earnings Before Interest and Tax (EBIT) | C8: =C5-SUM(C6:C7) -> 6.125 | D8: =D5-SUM(D6:D7) -> 16 | E8: =E5-SUM(E6:E7) -> 25.5 | F8: =F5-SUM(F6:F7) -> 11.25 | H8: =B8 -> Earnings Before Interest and Tax (EBIT) | I8: 0 | J8: =(D8-C8)/C8 -> 1.6122449 | K8: =(E8-D8)/D8 -> 0.59375 | L8: =(F8-E8)/E8 -> -0.55882353
B9: =SCF!B9 -> Interest expense | C9: =SCF!C9 -> 3.625 | D9: =SCF!D9 -> 3.5 | E9: =SCF!E9 -> 3 | F9: =SCF!F9 -> 2.5 | H9: =B9 -> Interest expense | I9: 0 | J9: =(D9-C9)/C9 -> -0.034482759 | K9: =(E9-D9)/D9 -> -0.14285714 | L9: =(F9-E9)/E9 -> -0.16666667
B10: =SCF!B10 -> Earnings Before Tax (EBT) | C10: =C8-C9 -> 2.5 | D10: =D8-D9 -> 12.5 | E10: =E8-E9 -> 22.5 | F10: =F8-F9 -> 8.75 | H10: =B10 -> Earnings Before Tax (EBT) | I10: 0 | J10: =(D10-C10)/C10 -> 4 | K10: =(E10-D10)/D10 -> 0.8 | L10: =(F10-E10)/E10 -> -0.61111111
A11: =SCF!A11 -> 0.3 | B11: =SCF!B11 -> Tax expense | C11: =C10*$A$11 -> 0.75 | D11: =D10*$A$11 -> 3.75 | E11: =E10*$A$11 -> 6.75 | F11: =F10*$A$11 -> 2.625 | H11: =B11 -> Tax expense | I11: 0 | J11: =(D11-C11)/C11 -> 4 | K11: =(E11-D11)/D11 -> 0.8 | L11: =(F11-E11)/E11 -> -0.61111111
B12: =SCF!B12 -> Net Income (NI) | C12: =C10-C11 -> 1.75 | D12: =D10-D11 -> 8.75 | E12: =E10-E11 -> 15.75 | F12: =F10-F11 -> 6.125 | H12: =B12 -> Net Income (NI) | I12: 0 | J12: =(D12-C12)/C12 -> 4 | K12: =(E12-D12)/D12 -> 0.8 | L12: =(F12-E12)/E12 -> -0.61111111
B13: =SCF!B13 -> Dividends (in million $) | C13: =SCF!C13 -> 1.25 | D13: =SCF!D13 -> 5 | E13: =SCF!E13 -> 8.25 | F13: =SCF!F13 -> 4.875
B14: =SCF!B14 -> Additional Retained Earnings (in million $) | C14: =C12-C13 -> 0.5 | D14: =D12-D13 -> 3.75 | E14: =E12-E13 -> 7.5 | F14: =F12-F13 -> 1.25
B16: =SCF!B16 -> Shares Outstanding (in million) | C16: =SCF!C16 -> 25 | D16: =SCF!D16 -> 25 | E16: =SCF!E16 -> 25 | F16: =SCF!F16 -> 25
B17: =SCF!B17 -> Market Value per Share ($/Share) | C17: =SCF!C17 -> 5 | D17: =SCF!D17 -> 7.5 | E17: =SCF!E17 -> 8.75 | F17: =SCF!F17 -> 6.25
B19: Balance sheet as at 30 June (in Million $) | H19: Percentage Change (yoy)
C20: =C2 -> 2019 | D20: =D2 -> 2020 | E20: =E2 -> 2021 | F20: =F2 -> 2022 | I20: =C20 -> 2019 | J20: =D20 -> 2020 | K20: =E20 -> 2021 | L20: =F20 -> 2022
B21: =SCF!B21 -> Current Assets | H21: =B21 -> Current Assets
B22: =SCF!B22 -> Cash | C22: =SCF!C22 -> 2.5 | D22: =SCF!D22 -> 6.25 | E22: =SCF!E22 -> 7.5 | F22: =SCF!F22 -> 10 | H22: =B22 -> Cash | I22: 0 | J22: =(D22-C22)/C22 -> 1.5 | K22: =(E22-D22)/D22 -> 0.2 | L22: =(F22-E22)/E22 -> 0.33333333
B23: =SCF!B23 -> Accounts Receivable | C23: =SCF!C23 -> 3.75 | D23: =SCF!D23 -> 8.75 | E23: =SCF!E23 -> 10 | F23: =SCF!F23 -> 13.75 | H23: =B23 -> Accounts Receivable | I23: 0 | J23: =(D23-C23)/C23 -> 1.3333333 | K23: =(E23-D23)/D23 -> 0.14285714 | L23: =(F23-E23)/E23 -> 0.375
B24: =SCF!B24 -> Inventories | C24: =SCF!C24 -> 11.25 | D24: =SCF!D24 -> 16.875 | E24: =SCF!E24 -> 18.75 | F24: =SCF!F24 -> 15 | H24: =B24 -> Inventories | I24: 0 | J24: =(D24-C24)/C24 -> 0.5 | K24: =(E24-D24)/D24 -> 0.11111111 | L24: =(F24-E24)/E24 -> -0.2
B25: =SCF!B25 -> Other Current Assets | C25: =SCF!C25 -> 1.25 | D25: =SCF!D25 -> 3.75 | E25: =SCF!E25 -> 4.375 | F25: =SCF!F25 -> 7.5 | H25: =B25 -> Other Current Assets | I25: 0 | J25: =(D25-C25)/C25 -> 2 | K25: =(E25-D25)/D25 -> 0.16666667 | L25: =(F25-E25)/E25 -> 0.71428571
B26: =SCF!B26 -> Total Current Assets | C26: =SUM(C22:C25) -> 18.75 | D26: =SUM(D22:D25) -> 35.625 | E26: =SUM(E22:E25) -> 40.625 | F26: =SUM(F22:F25) -> 46.25 | H26: =B26 -> Total Current Assets | I26: 0 | J26: =(D26-C26)/C26 -> 0.9 | K26: =(E26-D26)/D26 -> 0.14035088 | L26: =(F26-E26)/E26 -> 0.13846154
B28: =SCF!B28 -> Long Term Assets | H28: =B28 -> Long Term Assets
B29: =SCF!B29 -> PPE (Gross) | C29: =SCF!C29 -> 75 | D29: =SCF!D29 -> 87.5 | E29: =SCF!E29 -> 100 | F29: =SCF!F29 -> 112.5 | H29: =B29 -> PPE (Gross) | I29: 0 | J29: =(D29-C29)/C29 -> 0.16666667 | K29: =(E29-D29)/D29 -> 0.14285714 | L29: =(F29-E29)/E29 -> 0.125
B30: =SCF!B30 -> Acc Dep | C30: =SCF!C30 -> 37.5 | D30: =SCF!D30 -> 41.875 | E30: =SCF!E30 -> 46.875 | F30: =SCF!F30 -> 52.5 | H30: =B30 -> Acc Dep | I30: 0 | J30: =(D30-C30)/C30 -> 0.11666667 | K30: =(E30-D30)/D30 -> 0.11940299 | L30: =(F30-E30)/E30 -> 0.12
B31: =SCF!B31 -> PPE (Net) | C31: =C29-C30 -> 37.5 | D31: =D29-D30 -> 45.625 | E31: =E29-E30 -> 53.125 | F31: =F29-F30 -> 60 | H31: =B31 -> PPE (Net) | I31: 0 | J31: =(D31-C31)/C31 -> 0.21666667 | K31: =(E31-D31)/D31 -> 0.16438356 | L31: =(F31-E31)/E31 -> 0.12941176
B32: =SCF!B32 -> Goodwill | C32: =SCF!C32 -> 6.25 | D32: =SCF!D32 -> 6.25 | E32: =SCF!E32 -> 6.25 | F32: =SCF!F32 -> 6.25 | H32: =B32 -> Goodwill | I32: 0 | J32: =(D32-C32)/C32 -> 0 | K32: =(E32-D32)/D32 -> 0 | L32: =(F32-E32)/E32 -> 0
B33: =SCF!B33 -> Total Long Term Assets | C33: =SUM(C31:C32) -> 43.75 | D33: =SUM(D31:D32) -> 51.875 | E33: =SUM(E31:E32) -> 59.375 | F33: =SUM(F31:F32) -> 66.25 | H33: =B33 -> Total Long Term Assets | I33: 0 | J33: =(D33-C33)/C33 -> 0.18571429 | K33: =(E33-D33)/D33 -> 0.14457831 | L33: =(F33-E33)/E33 -> 0.11578947
B35: =SCF!B35 -> Total Assets | C35: =C26+C33 -> 62.5 | D35: =D26+D33 -> 87.5 | E35: =E26+E33 -> 100 | F35: =F26+F33 -> 112.5 | H35: =B35 -> Total Assets | I35: 0 | J35: =(D35-C35)/C35 -> 0.4 | K35: =(E35-D35)/D35 -> 0.14285714 | L35: =(F35-E35)/E35 -> 0.125
B37: =SCF!B37 -> Current Liabilities | H37: =B37 -> Current Liabilities
B38: =SCF!B38 -> Accounts Payable | C38: =SCF!C38 -> 6.25 | D38: =SCF!D38 -> 15 | E38: =SCF!E38 -> 31.25 | F38: =SCF!F38 -> 32.5 | H38: =B38 -> Accounts Payable | I38: 0 | J38: =(D38-C38)/C38 -> 1.4 | K38: =(E38-D38)/D38 -> 1.0833333 | L38: =(F38-E38)/E38 -> 0.04
B39: =SCF!B39 -> Notes Payable | C39: =SCF!C39 -> 3.75 | D39: =SCF!D39 -> 16.25 | E39: =SCF!E39 -> 10 | F39: =SCF!F39 -> 22.5 | H39: =B39 -> Notes Payable | I39: 0 | J39: =(D39-C39)/C39 -> 3.3333333 | K39: =(E39-D39)/D39 -> -0.38461538 | L39: =(F39-E39)/E39 -> 1.25
B40: =SCF!B40 -> Current Portion of LTD | C40: =SCF!C40 -> 5 | D40: =SCF!D40 -> 5 | E40: =SCF!E40 -> 5 | F40: =SCF!F40 -> 5 | H40: =B40 -> Current Portion of LTD | I40: 0 | J40: =(D40-C40)/C40 -> 0 | K40: =(E40-D40)/D40 -> 0 | L40: =(F40-E40)/E40 -> 0
B41: =SCF!B41 -> Total Current Liabilities | C41: =SUM(C38:C40) -> 15 | D41: =SUM(D38:D40) -> 36.25 | E41: =SUM(E38:E40) -> 46.25 | F41: =SUM(F38:F40) -> 60 | H41: =B41 -> Total Current Liabilities | I41: 0 | J41: =(D41-C41)/C41 -> 1.4166667 | K41: =(E41-D41)/D41 -> 0.27586207 | L41: =(F41-E41)/E41 -> 0.2972973
B43: =SCF!B43 -> Long Term Liabilities | H43: =B43 -> Long Term Liabilities
B44: =SCF!B44 -> Long Term Loan | C44: =SCF!C44 -> 25 | D44: =SCF!D44 -> 20 | E44: =SCF!E44 -> 15 | F44: =SCF!F44 -> 10 | H44: =B44 -> Long Term Loan | I44: 0 | J44: =(D44-C44)/C44 -> -0.2 | K44: =(E44-D44)/D44 -> -0.25 | L44: =(F44-E44)/E44 -> -0.33333333
B45: =SCF!B45 -> Bonds Payable | C45: =SCF!C45 -> 7.5 | D45: =SCF!D45 -> 10 | E45: =SCF!E45 -> 10 | F45: =SCF!F45 -> 10 | H45: =B45 -> Bonds Payable | I45: 0 | J45: =(D45-C45)/C45 -> 0.33333333 | K45: =(E45-D45)/D45 -> 0 | L45: =(F45-E45)/E45 -> 0
B46: =SCF!B46 -> Total Long Term Liabilities | C46: =SUM(C44:C45) -> 32.5 | D46: =SUM(D44:D45) -> 30 | E46: =SUM(E44:E45) -> 25 | F46: =SUM(F44:F45) -> 20 | H46: =B46 -> Total Long Term Liabilities | I46: 0 | J46: =(D46-C46)/C46 -> -0.076923077 | K46: =(E46-D46)/D46 -> -0.16666667 | L46: =(F46-E46)/E46 -> -0.2
B48: =SCF!B48 -> Shareholders' Equity | H48: =B48 -> Shareholders' Equity
B49: =SCF!B49 -> Contributed Capital | C49: =SCF!C49 -> 10 | D49: =SCF!D49 -> 12.5 | E49: =SCF!E49 -> 12.5 | F49: =SCF!F49 -> 15 | H49: =B49 -> Contributed Capital | I49: 0 | J49: =(D49-C49)/C49 -> 0.25 | K49: =(E49-D49)/D49 -> 0 | L49: =(F49-E49)/E49 -> 0.2
B50: =SCF!B50 -> Retained Earnings | C50: =SCF!C50 -> 5 | D50: =C50+D14 -> 8.75 | E50: =D50+E14 -> 16.25 | F50: =E50+F14 -> 17.5 | H50: =B50 -> Retained Earnings | I50: 0 | J50: =(D50-C50)/C50 -> 0.75 | K50: =(E50-D50)/D50 -> 0.85714286 | L50: =(F50-E50)/E50 -> 0.076923077
B51: =SCF!B51 -> Total Shareholders' Equity | C51: =SUM(C49:C50) -> 15 | D51: =SUM(D49:D50) -> 21.25 | E51: =SUM(E49:E50) -> 28.75 | F51: =SUM(F49:F50) -> 32.5 | H51: =B51 -> Total Shareholders' Equity | I51: 0 | J51: =(D51-C51)/C51 -> 0.41666667 | K51: =(E51-D51)/D51 -> 0.35294118 | L51: =(F51-E51)/E51 -> 0.13043478
B53: =SCF!B53 -> Total Liabilities and Equity | C53: =C41+C46+C51 -> 62.5 | D53: =D41+D46+D51 -> 87.5 | E53: =E41+E46+E51 -> 100 | F53: =F41+F46+F51 -> 112.5 | H53: =B53 -> Total Liabilities and Equity | I53: 0 | J53: =(D53-C53)/C53 -> 0.4 | K53: =(E53-D53)/D53 -> 0.14285714 | L53: =(F53-E53)/E53 -> 0.125
B55: =SCF!B55 -> Balance | C55: =C35-C53 -> 0 | D55: =D35-D53 -> 0 | E55: =E35-E53 -> 0 | F55: =F35-F53 -> 0

Sheet VA
B1: Income Statement for the years ended 30 June (in Million $) | H1: Vertical Analysis
C2: =SCF!C2 -> 2019 | D2: =SCF!D2 -> 2020 | E2: =SCF!E2 -> 2021 | F2: =SCF!F2 -> 2022 | I2: =C2 -> 2019 | J2: =D2 -> 2020 | K2: =E2 -> 2021 | L2: =F2 -> 2022
B3: =SCF!B3 -> Sales | C3: =SCF!C3 -> 50 | D3: =SCF!D3 -> 75 | E3: =SCF!E3 -> 100 | F3: =SCF!F3 -> 125 | H3: =B3 -> Sales | I3: =C3/C3 -> 1 | J3: =D3/D3 -> 1 | K3: =E3/E3 -> 1 | L3: =F3/F3 -> 1
B4: =SCF!B4 -> Cost of Goods Sold (COGS) | C4: =SCF!C4 -> 37.5 | D4: =SCF!D4 -> 50 | E4: =SCF!E4 -> 62.5 | F4: =SCF!F4 -> 100 | H4: =B4 -> Cost of Goods Sold (COGS) | I4: =C4/C3 -> 0.75 | J4: =D4/D3 -> 0.66666667 | K4: =E4/E3 -> 0.625 | L4: =F4/F3 -> 0.8
B5: =SCF!B5 -> Gross Profit | C5: =C3-C4 -> 12.5 | D5: =D3-D4 -> 25 | E5: =E3-E4 -> 37.5 | F5: =F3-F4 -> 25 | H5: =B5 -> Gross Profit | I5: =C5/C3 -> 0.25 | J5: =D5/D3 -> 0.33333333 | K5: =E5/E3 -> 0.375 | L5: =F5/F3 -> 0.2
B6: =SCF!B6 -> Selling, General & Administrative Expenses | C6: =SCF!C6 -> 2.625 | D6: =SCF!D6 -> 4.625 | E6: =SCF!E6 -> 7 | F6: =SCF!F6 -> 8.125 | H6: =B6 -> Selling, General & Administrative Expenses | I6: =C6/C3 -> 0.0525 | J6: =D6/D3 -> 0.061666667 | K6: =E6/E3 -> 0.07 | L6: =F6/F3 -> 0.065
B7: =SCF!B7 -> Depreciation | C7: =SCF!C7 -> 3.75 | D7: =SCF!D7 -> 4.375 | E7: =SCF!E7 -> 5 | F7: =SCF!F7 -> 5.625 | H7: =B7 -> Depreciation | I7: =C7/C3 -> 0.075 | J7: =D7/D3 -> 0.058333333 | K7: =E7/E3 -> 0.05 | L7: =F7/F3 -> 0.045
B8: =SCF!B8 -> Earnings Before Interest and Tax (EBIT) | C8: =C5-SUM(C6:C7) -> 6.125 | D8: =D5-SUM(D6:D7) -> 16 | E8: =E5-SUM(E6:E7) -> 25.5 | F8: =F5-SUM(F6:F7) -> 11.25 | H8: =B8 -> Earnings Before Interest and Tax (EBIT) | I8: =C8/C3 -> 0.1225 | J8: =D8/D3 -> 0.21333333 | K8: =E8/E3 -> 0.255 | L8: =F8/F3 -> 0.09
B9: =SCF!B9 -> Interest expense | C9: =SCF!C9 -> 3.625 | D9: =SCF!D9 -> 3.5 | E9: =SCF!E9 -> 3 | F9: =SCF!F9 -> 2.5 | H9: =B9 -> Interest expense | I9: =C9/C3 -> 0.0725 | J9: =D9/D3 -> 0.046666667 | K9: =E9/E3 -> 0.03 | L9: =F9/F3 -> 0.02
B10: =SCF!B10 -> Earnings Before Tax (EBT) | C10: =C8-C9 -> 2.5 | D10: =D8-D9 -> 12.5 | E10: =E8-E9 -> 22.5 | F10: =F8-F9 -> 8.75 | H10: =B10 -> Earnings Before Tax (EBT) | I10: =C10/C3 -> 0.05 | J10: =D10/D3 -> 0.16666667 | K10: =E10/E3 -> 0.225 | L10: =F10/F3 -> 0.07
A11: =SCF!A11 -> 0.3 | B11: =SCF!B11 -> Tax expense | C11: =C10*$A$11 -> 0.75 | D11: =D10*$A$11 -> 3.75 | E11: =E10*$A$11 -> 6.75 | F11: =F10*$A$11 -> 2.625 | H11: =B11 -> Tax expense | I11: =C11/C3 -> 0.015 | J11: =D11/D3 -> 0.05 | K11: =E11/E3 -> 0.0675 | L11: =F11/F3 -> 0.021
B12: =SCF!B12 -> Net Income (NI) | C12: =C10-C11 -> 1.75 | D12: =D10-D11 -> 8.75 | E12: =E10-E11 -> 15.75 | F12: =F10-F11 -> 6.125 | H12: =B12 -> Net Income (NI) | I12: =C12/C3 -> 0.035 | J12: =D12/D3 -> 0.11666667 | K12: =E12/E3 -> 0.1575 | L12: =F12/F3 -> 0.049
B13: =SCF!B13 -> Dividends (in million $) | C13: =SCF!C13 -> 1.25 | D13: =SCF!D13 -> 5 | E13: =SCF!E13 -> 8.25 | F13: =SCF!F13 -> 4.875
B14: =SCF!B14 -> Additional Retained Earnings (in million $) | C14: =C12-C13 -> 0.5 | D14: =D12-D13 -> 3.75 | E14: =E12-E13 -> 7.5 | F14: =F12-F13 -> 1.25
B16: =SCF!B16 -> Shares Outstanding (in million) | C16: =SCF!C16 -> 25 | D16: =SCF!D16 -> 25 | E16: =SCF!E16 -> 25 | F16: =SCF!F16 -> 25
B17: =SCF!B17 -> Market Value per Share ($/Share) | C17: =SCF!C17 -> 5 | D17: =SCF!D17 -> 7.5 | E17: =SCF!E17 -> 8.75 | F17: =SCF!F17 -> 6.25
B19: Balance sheet as at 30 June (in Million $) | H19: Vertical Analysis
C20: =C2 -> 2019 | D20: =D2 -> 2020 | E20: =E2 -> 2021 | F20: =F2 -> 2022 | I20: =C20 -> 2019 | J20: =D20 -> 2020 | K20: =E20 -> 2021 | L20: =F20 -> 2022
B21: =SCF!B21 -> Current Assets | H21: =B21 -> Current Assets
B22: =SCF!B22 -> Cash | C22: =SCF!C22 -> 2.5 | D22: =SCF!D22 -> 6.25 | E22: =SCF!E22 -> 7.5 | F22: =SCF!F22 -> 10 | H22: =B22 -> Cash | I22: =C22/C35 -> 0.04 | J22: =D22/D35 -> 0.071428571 | K22: =E22/E35 -> 0.075 | L22: =F22/F35 -> 0.088888889
B23: =SCF!B23 -> Accounts Receivable | C23: =SCF!C23 -> 3.75 | D23: =SCF!D23 -> 8.75 | E23: =SCF!E23 -> 10 | F23: =SCF!F23 -> 13.75 | H23: =B23 -> Accounts Receivable | I23: =C23/C35 -> 0.06 | J23: =D23/D35 -> 0.1 | K23: =E23/E35 -> 0.1 | L23: =F23/F35 -> 0.12222222
B24: =SCF!B24 -> Inventories | C24: =SCF!C24 -> 11.25 | D24: =SCF!D24 -> 16.875 | E24: =SCF!E24 -> 18.75 | F24: =SCF!F24 -> 15 | H24: =B24 -> Inventories | I24: =C24/C35 -> 0.18 | J24: =D24/D35 -> 0.19285714 | K24: =E24/E35 -> 0.1875 | L24: =F24/F35 -> 0.13333333
B25: =SCF!B25 -> Other Current Assets | C25: =SCF!C25 -> 1.25 | D25: =SCF!D25 -> 3.75 | E25: =SCF!E25 -> 4.375 | F25: =SCF!F25 -> 7.5 | H25: =B25 -> Other Current Assets | I25: =C25/C35 -> 0.02 | J25: =D25/D35 -> 0.042857143 | K25: =E25/E35 -> 0.04375 | L25: =F25/F35 -> 0.066666667
B26: =SCF!B26 -> Total Current Assets | C26: =SUM(C22:C25) -> 18.75 | D26: =SUM(D22:D25) -> 35.625 | E26: =SUM(E22:E25) -> 40.625 | F26: =SUM(F22:F25) -> 46.25 | H26: =B26 -> Total Current Assets | I26: =C26/C35 -> 0.3 | J26: =D26/D35 -> 0.40714286 | K26: =E26/E35 -> 0.40625 | L26: =F26/F35 -> 0.41111111
B28: =SCF!B28 -> Long Term Assets | H28: =B28 -> Long Term Assets
B29: =SCF!B29 -> PPE (Gross) | C29: =SCF!C29 -> 75 | D29: =SCF!D29 -> 87.5 | E29: =SCF!E29 -> 100 | F29: =SCF!F29 -> 112.5 | H29: =B29 -> PPE (Gross) | I29: =C29/C33 -> 1.7142857 | J29: =D29/D33 -> 1.686747 | K29: =E29/E33 -> 1.6842105 | L29: =F29/F33 -> 1.6981132
B30: =SCF!B30 -> Acc Dep | C30: =SCF!C30 -> 37.5 | D30: =SCF!D30 -> 41.875 | E30: =SCF!E30 -> 46.875 | F30: =SCF!F30 -> 52.5 | H30: =B30 -> Acc Dep | I30: =C30/C35 -> 0.6 | J30: =D30/D35 -> 0.47857143 | K30: =E30/E35 -> 0.46875 | L30: =F30/F35 -> 0.46666667
B31: =SCF!B31 -> PPE (Net) | C31: =C29-C30 -> 37.5 | D31: =D29-D30 -> 45.625 | E31: =E29-E30 -> 53.125 | F31: =F29-F30 -> 60 | H31: =B31 -> PPE (Net) | I31: =C31/C33 -> 0.85714286 | J31: =D31/D33 -> 0.87951807 | K31: =E31/E33 -> 0.89473684 | L31: =F31/F33 -> 0.90566038
B32: =SCF!B32 -> Goodwill | C32: =SCF!C32 -> 6.25 | D32: =SCF!D32 -> 6.25 | E32: =SCF!E32 -> 6.25 | F32: =SCF!F32 -> 6.25 | H32: =B32 -> Goodwill | I32: =C32/C35 -> 0.1 | J32: =D32/D35 -> 0.071428571 | K32: =E32/E35 -> 0.0625 | L32: =F32/F35 -> 0.055555556
B33: =SCF!B33 -> Total Long Term Assets | C33: =SUM(C31:C32) -> 43.75 | D33: =SUM(D31:D32) -> 51.875 | E33: =SUM(E31:E32) -> 59.375 | F33: =SUM(F31:F32) -> 66.25 | H33: =B33 -> Total Long Term Assets | I33: =C33/C35 -> 0.7 | J33: =D33/D35 -> 0.59285714 | K33: =E33/E35 -> 0.59375 | L33: =F33/F35 -> 0.58888889
B35: =SCF!B35 -> Total Assets | C35: =C26+C33 -> 62.5 | D35: =D26+D33 -> 87.5 | E35: =E26+E33 -> 100 | F35: =F26+F33 -> 112.5 | H35: =B35 -> Total Assets | I35: =C35/C35 -> 1 | J35: =D35/D35 -> 1 | K35: =E35/E35 -> 1 | L35: =F35/F35 -> 1
B37: =SCF!B37 -> Current Liabilities | H37: =B37 -> Current Liabilities
B38: =SCF!B38 -> Accounts Payable | C38: =SCF!C38 -> 6.25 | D38: =SCF!D38 -> 15 | E38: =SCF!E38 -> 31.25 | F38: =SCF!F38 -> 32.5 | H38: =B38 -> Accounts Payable | I38: =C38/C53 -> 0.1 | J38: =D38/D53 -> 0.17142857 | K38: =E38/E53 -> 0.3125 | L38: =F38/F53 -> 0.28888889
B39: =SCF!B39 -> Notes Payable | C39: =SCF!C39 -> 3.75 | D39: =SCF!D39 -> 16.25 | E39: =SCF!E39 -> 10 | F39: =SCF!F39 -> 22.5 | H39: =B39 -> Notes Payable | I39: =C39/C53 -> 0.06 | J39: =D39/D53 -> 0.18571429 | K39: =E39/E53 -> 0.1 | L39: =F39/F53 -> 0.2
B40: =SCF!B40 -> Current Portion of LTD | C40: =SCF!C40 -> 5 | D40: =SCF!D40 -> 5 | E40: =SCF!E40 -> 5 | F40: =SCF!F40 -> 5 | H40: =B40 -> Current Portion of LTD | I40: =C40/C53 -> 0.08 | J40: =D40/D53 -> 0.057142857 | K40: =E40/E53 -> 0.05 | L40: =F40/F53 -> 0.044444444
B41: =SCF!B41 -> Total Current Liabilities | C41: =SUM(C38:C40) -> 15 | D41: =SUM(D38:D40) -> 36.25 | E41: =SUM(E38:E40) -> 46.25 | F41: =SUM(F38:F40) -> 60 | H41: =B41 -> Total Current Liabilities | I41: =C41/C53 -> 0.24 | J41: =D41/D53 -> 0.41428571 | K41: =E41/E53 -> 0.4625 | L41: =F41/F53 -> 0.53333333
B43: =SCF!B43 -> Long Term Liabilities | H43: =B43 -> Long Term Liabilities
B44: =SCF!B44 -> Long Term Loan | C44: =SCF!C44 -> 25 | D44: =SCF!D44 -> 20 | E44: =SCF!E44 -> 15 | F44: =SCF!F44 -> 10 | H44: =B44 -> Long Term Loan | I44: =C44/C53 -> 0.4 | J44: =D44/D53 -> 0.22857143 | K44: =E44/E53 -> 0.15 | L44: =F44/F53 -> 0.088888889
B45: =SCF!B45 -> Bonds Payable | C45: =SCF!C45 -> 7.5 | D45: =SCF!D45 -> 10 | E45: =SCF!E45 -> 10 | F45: =SCF!F45 -> 10 | H45: =B45 -> Bonds Payable | I45: =C45/C53 -> 0.12 | J45: =D45/D53 -> 0.11428571 | K45: =E45/E53 -> 0.1 | L45: =F45/F53 -> 0.088888889
B46: =SCF!B46 -> Total Long Term Liabilities | C46: =SUM(C44:C45) -> 32.5 | D46: =SUM(D44:D45) -> 30 | E46: =SUM(E44:E45) -> 25 | F46: =SUM(F44:F45) -> 20 | H46: =B46 -> Total Long Term Liabilities | I46: =C46/C53 -> 0.52 | J46: =D46/D53 -> 0.34285714 | K46: =E46/E53 -> 0.25 | L46: =F46/F53 -> 0.17777778
B48: =SCF!B48 -> Shareholders' Equity | H48: =B48 -> Shareholders' Equity
B49: =SCF!B49 -> Contributed Capital | C49: =SCF!C49 -> 10 | D49: =SCF!D49 -> 12.5 | E49: =SCF!E49 -> 12.5 | F49: =SCF!F49 -> 15 | H49: =B49 -> Contributed Capital | I49: =C49/C53 -> 0.16 | J49: =D49/D53 -> 0.14285714 | K49: =E49/E53 -> 0.125 | L49: =F49/F53 -> 0.13333333
B50: =SCF!B50 -> Retained Earnings | C50: =SCF!C50 -> 5 | D50: =C50+D14 -> 8.75 | E50: =D50+E14 -> 16.25 | F50: =E50+F14 -> 17.5 | H50: =B50 -> Retained Earnings | I50: =C50/C53 -> 0.08 | J50: =D50/D53 -> 0.1 | K50: =E50/E53 -> 0.1625 | L50: =F50/F53 -> 0.15555556
B51: =SCF!B51 -> Total Shareholders' Equity | C51: =SUM(C49:C50) -> 15 | D51: =SUM(D49:D50) -> 21.25 | E51: =SUM(E49:E50) -> 28.75 | F51: =SUM(F49:F50) -> 32.5 | H51: =B51 -> Total Shareholders' Equity | I51: =C51/C53 -> 0.24 | J51: =D51/D53 -> 0.24285714 | K51: =E51/E53 -> 0.2875 | L51: =F51/F53 -> 0.28888889
B53: =SCF!B53 -> Total Liabilities and Equity | C53: =C41+C46+C51 -> 62.5 | D53: =D41+D46+D51 -> 87.5 | E53: =E41+E46+E51 -> 100 | F53: =F41+F46+F51 -> 112.5 | H53: =B53 -> Total Liabilities and Equity | I53: =C53/C53 -> 1 | J53: =D53/D53 -> 1 | K53: =E53/E53 -> 1 | L53: =F53/F53 -> 1
B55: =SCF!B55 -> Balance | C55: =C35-C53 -> 0 | D55: =D35-D53 -> 0 | E55: =E35-E53 -> 0 | F55: =F35-F53 -> 0

Sheet Ratio
B1: Income Statement for the years ended 30 June (in Million $) | H1: Financial Ratio
C2: =SCF!C2 -> 2019 | D2: =SCF!D2 -> 2020 | E2: =SCF!E2 -> 2021 | F2: =SCF!F2 -> 2022 | I2: Unit | J2: =C2 -> 2019 | K2: =D2 -> 2020 | L2: =E2 -> 2021 | M2: =F2 -> 2022
B3: =SCF!B3 -> Sales | C3: =SCF!C3 -> 50 | D3: =SCF!D3 -> 75 | E3: =SCF!E3 -> 100 | F3: =SCF!F3 -> 125 | H3: Liquidity Ratios
B4: =SCF!B4 -> Cost of Goods Sold (COGS) | C4: =SCF!C4 -> 37.5 | D4: =SCF!D4 -> 50 | E4: =SCF!E4 -> 62.5 | F4: =SCF!F4 -> 100 | H4: Current Ratio | I4: Times | J4: =C26/C41 -> 1.25 | K4: =D26/D41 -> 0.98275862 | L4: =E26/E41 -> 0.87837838 | M4: =F26/F41 -> 0.77083333
B5: =SCF!B5 -> Gross Profit | C5: =C3-C4 -> 12.5 | D5: =D3-D4 -> 25 | E5: =E3-E4 -> 37.5 | F5: =F3-F4 -> 25 | H5: Quick Ratio | I5: Times | J5: =(C26-C24)/C41 -> 0.5 | K5: =(D26-D24)/D41 -> 0.51724138 | L5: =(E26-E24)/E41 -> 0.47297297 | M5: =(F26-F24)/F41 -> 0.52083333
B6: =SCF!B6 -> Selling, General & Administrative Expenses | C6: =SCF!C6 -> 2.625 | D6: =SCF!D6 -> 4.625 | E6: =SCF!E6 -> 7 | F6: =SCF!F6 -> 8.125 | H6: Cash Ratio | I6: Times | J6: =C22/C41 -> 0.16666667 | K6: =D22/D41 -> 0.17241379 | L6: =E22/E41 -> 0.16216216 | M6: =F22/F41 -> 0.16666667
B7: =SCF!B7 -> Depreciation | C7: =SCF!C7 -> 3.75 | D7: =SCF!D7 -> 4.375 | E7: =SCF!E7 -> 5 | F7: =SCF!F7 -> 5.625 | H7: NWC | I7: $ | J7: =C26-C41 -> 3.75 | K7: =D26-D41 -> -0.625 | L7: =E26-E41 -> -5.625 | M7: =F26-F41 -> -13.75
B8: =SCF!B8 -> Earnings Before Interest and Tax (EBIT) | C8: =C5-SUM(C6:C7) -> 6.125 | D8: =D5-SUM(D6:D7) -> 16 | E8: =E5-SUM(E6:E7) -> 25.5 | F8: =F5-SUM(F6:F7) -> 11.25 | H8: NWC to Total Assets | I8: % | J8: =J7/C35 -> 0.06 | K8: =K7/D35 -> -0.0071428571 | L8: =L7/E35 -> -0.05625 | M8: =M7/F35 -> -0.12222222
B9: =SCF!B9 -> Interest expense | C9: =SCF!C9 -> 3.625 | D9: =SCF!D9 -> 3.5 | E9: =SCF!E9 -> 3 | F9: =SCF!F9 -> 2.5 | H9: Interval Measure | I9: Days | J9: =C26/(SUM(C6,C4,C7)/365) -> 155.98291 | K9: =D26/(SUM(D6,D4,D7)/365) -> 220.39195 | L9: =E26/(SUM(E6,E4,E7)/365) -> 199.03523 | M9: =F26/(SUM(F6,F4,F7)/365) -> 148.40659
B10: =SCF!B10 -> Earnings Before Tax (EBT) | C10: =C8-C9 -> 2.5 | D10: =D8-D9 -> 12.5 | E10: =E8-E9 -> 22.5 | F10: =F8-F9 -> 8.75
A11: =SCF!A11 -> 0.3 | B11: =SCF!B11 -> Tax expense | C11: =C10*$A$11 -> 0.75 | D11: =D10*$A$11 -> 3.75 | E11: =E10*$A$11 -> 6.75 | F11: =F10*$A$11 -> 2.625 | H11: Profitability Ratio
B12: =SCF!B12 -> Net Income (NI) | C12: =C10-C11 -> 1.75 | D12: =D10-D11 -> 8.75 | E12: =E10-E11 -> 15.75 | F12: =F10-F11 -> 6.125 | H12: Gross Profit Margin (GPM) | I12: % | J12: =C5/C3 -> 0.25 | K12: =D5/D3 -> 0.33333333 | L12: =E5/E3 -> 0.375 | M12: =F5/F3 -> 0.2
B13: =SCF!B13 -> Dividends (in million $) | C13: =SCF!C13 -> 1.25 | D13: =SCF!D13 -> 5 | E13: =SCF!E13 -> 8.25 | F13: =SCF!F13 -> 4.875 | H13: Operating Profit Margin (OPM) | I13: % | J13: =C8/C3 -> 0.1225 | K13: =D8/D3 -> 0.21333333 | L13: =E8/E3 -> 0.255 | M13: =F8/F3 -> 0.09
B14: =SCF!B14 -> Additional Retained Earnings (in million $) | C14: =C12-C13 -> 0.5 | D14: =D12-D13 -> 3.75 | E14: =E12-E13 -> 7.5 | F14: =F12-F13 -> 1.25 | H14: Profit Margin (PM) | I14: % | J14: =C12/C3 -> 0.035 | K14: =D12/D3 -> 0.11666667 | L14: =E12/E3 -> 0.1575 | M14: =F12/F3 -> 0.049
H15: Return on Asset (ROA) | I15: % | J15: =C12/C35 -> 0.028 | K15: =D12/D35 -> 0.1 | L15: =E12/E35 -> 0.1575 | M15: =F12/F35 -> 0.054444444
B16: =SCF!B16 -> Shares Outstanding (in million) | C16: =SCF!C16 -> 25 | D16: =SCF!D16 -> 25 | E16: =SCF!E16 -> 25 | F16: =SCF!F16 -> 25 | H16: Return on Equity (ROE) | I16: % | J16: =C12/C51 -> 0.11666667 | K16: =D12/D51 -> 0.41176471 | L16: =E12/E51 -> 0.54782609 | M16: =F12/F51 -> 0.18846154
B17: =SCF!B17 -> Market Value per Share ($/Share) | C17: =SCF!C17 -> 5 | D17: =SCF!D17 -> 7.5 | E17: =SCF!E17 -> 8.75 | F17: =SCF!F17 -> 6.25 | H17: Return on Capital Employed (ROCE) | I17: % | J17: =C8/(C35-C41) -> 0.12894737 | K17: =D8/(D35-D41) -> 0.31219512 | L17: =E8/(E35-E41) -> 0.4744186 | M17: =F8/(F35-F41) -> 0.21428571
B19: Balance sheet as at 30 June (in Million $) | H19: Financial Leverage Ratio
C20: =C2 -> 2019 | D20: =D2 -> 2020 | E20: =E2 -> 2021 | F20: =F2 -> 2022 | H20: Debt Ratio | I20: % | J20: =(C41+C46)/C35 -> 0.76 | K20: =(D41+D46)/D35 -> 0.75714286 | L20: =(E41+E46)/E35 -> 0.7125 | M20: =(F41+F46)/F35 -> 0.71111111
B21: =SCF!B21 -> Current Assets | H21: Equity Ratio | I21: % | J21: =C51/C35 -> 0.24 | K21: =D51/D35 -> 0.24285714 | L21: =E51/E35 -> 0.2875 | M21: =F51/F35 -> 0.28888889
B22: =SCF!B22 -> Cash | C22: =SCF!C22 -> 2.5 | D22: =SCF!D22 -> 6.25 | E22: =SCF!E22 -> 7.5 | F22: =SCF!F22 -> 10 | H22: Debt-to-Equity Ratio | I22: Times | J22: =(C41+C46)/C51 -> 3.1666667 | K22: =(D41+D46)/D51 -> 3.1176471 | L22: =(E41+E46)/E51 -> 2.4782609 | M22: =(F41+F46)/F51 -> 2.4615385
B23: =SCF!B23 -> Accounts Receivable | C23: =SCF!C23 -> 3.75 | D23: =SCF!D23 -> 8.75 | E23: =SCF!E23 -> 10 | F23: =SCF!F23 -> 13.75 | H23: Equity Multiplier (EM) | I23: Times | J23: =C35/C51 -> 4.1666667 | K23: =D35/D51 -> 4.1176471 | L23: =E35/E51 -> 3.4782609 | M23: =F35/F51 -> 3.4615385
B24: =SCF!B24 -> Inventories | C24: =SCF!C24 -> 11.25 | D24: =SCF!D24 -> 16.875 | E24: =SCF!E24 -> 18.75 | F24: =SCF!F24 -> 15 | H24: Fixed to Equity | I24: Times | J24: =C33/C51 -> 2.9166667 | K24: =D33/D51 -> 2.4411765 | L24: =E33/E51 -> 2.0652174 | M24: =F33/F51 -> 2.0384615
B25: =SCF!B25 -> Other Current Assets | C25: =SCF!C25 -> 1.25 | D25: =SCF!D25 -> 3.75 | E25: =SCF!E25 -> 4.375 | F25: =SCF!F25 -> 7.5 | H25: Long-Term Debt Ratio | I25: % | J25: =C46/(C46+C51) -> 0.68421053 | K25: =D46/(D46+D51) -> 0.58536585 | L25: =E46/(E46+E51) -> 0.46511628 | M25: =F46/(F46+F51) -> 0.38095238
B26: =SCF!B26 -> Total Current Assets | C26: =SUM(C22:C25) -> 18.75 | D26: =SUM(D22:D25) -> 35.625 | E26: =SUM(E22:E25) -> 40.625 | F26: =SUM(F22:F25) -> 46.25 | H26: Times Interest Earned (TIE) | I26: Times | J26: =C8/C9 -> 1.6896552 | K26: =D8/D9 -> 4.5714286 | L26: =E8/E9 -> 8.5 | M26: =F8/F9 -> 4.5
H27: Cash Coverage | I27: Times | J27: =(C8+C7)/C9 -> 2.7241379 | K27: =(D8+D7)/D9 -> 5.8214286 | L27: =(E8+E7)/E9 -> 10.166667 | M27: =(F8+F7)/F9 -> 6.75
B28: =SCF!B28 -> Long Term Assets | H28: Debt Service Coverage Ratio (DSCR) | I28: Times | J28: =C8/(C9+C41) -> 0.32885906 | K28: =D8/(D9+D41) -> 0.40251572 | L28: =E8/(E9+E41) -> 0.5177665 | M28: =F8/(F9+F41) -> 0.18
B29: =SCF!B29 -> PPE (Gross) | C29: =SCF!C29 -> 75 | D29: =SCF!D29 -> 87.5 | E29: =SCF!E29 -> 100 | F29: =SCF!F29 -> 112.5
B30: =SCF!B30 -> Acc Dep | C30: =SCF!C30 -> 37.5 | D30: =SCF!D30 -> 41.875 | E30: =SCF!E30 -> 46.875 | F30: =SCF!F30 -> 52.5 | H30: Asset Turnover Ratio
B31: =SCF!B31 -> PPE (Net) | C31: =C29-C30 -> 37.5 | D31: =D29-D30 -> 45.625 | E31: =E29-E30 -> 53.125 | F31: =F29-F30 -> 60 | H31: Inventory Turnover | I31: Times | J31: =C4/C24 -> 3.3333333 | K31: =D4/D24 -> 2.962963 | L31: =E4/E24 -> 3.3333333 | M31: =F4/F24 -> 6.6666667
B32: =SCF!B32 -> Goodwill | C32: =SCF!C32 -> 6.25 | D32: =SCF!D32 -> 6.25 | E32: =SCF!E32 -> 6.25 | F32: =SCF!F32 -> 6.25 | H32: Days' Sales in Inventory | I32: days | J32: =365/J31 -> 109.5 | K32: =365/K31 -> 123.1875 | L32: =365/L31 -> 109.5 | M32: =365/M31 -> 54.75
B33: =SCF!B33 -> Total Long Term Assets | C33: =SUM(C31:C32) -> 43.75 | D33: =SUM(D31:D32) -> 51.875 | E33: =SUM(E31:E32) -> 59.375 | F33: =SUM(F31:F32) -> 66.25 | H33: Receivables Turnover | I33: Times | J33: =C3/C23 -> 13.333333 | K33: =D3/D23 -> 8.5714286 | L33: =E3/E23 -> 10 | M33: =F3/F23 -> 9.0909091
H34: Days’ Sales in Receivables | I34: days | J34: =365/J33 -> 27.375 | K34: =365/K33 -> 42.583333 | L34: =365/L33 -> 36.5 | M34: =365/M33 -> 40.15
B35: =SCF!B35 -> Total Assets | C35: =C26+C33 -> 62.5 | D35: =D26+D33 -> 87.5 | E35: =E26+E33 -> 100 | F35: =F26+F33 -> 112.5 | H35: Payables Turnover | I35: Times | J35: =C4/C38 -> 6 | K35: =D4/D38 -> 3.3333333 | L35: =E4/E38 -> 2 | M35: =F4/F38 -> 3.0769231
H36: Days’ Sales in Payables | I36: days | J36: =365/J35 -> 60.833333 | K36: =365/K35 -> 109.5 | L36: =365/L35 -> 182.5 | M36: =365/M35 -> 118.625
B37: =SCF!B37 -> Current Liabilities | H37: Cash Conversion Cycle (CCC) | I37: days | J37: =J32+J34-J36 -> 76.041667 | K37: =K32+K34-K36 -> 56.270833 | L37: =L32+L34-L36 -> -36.5 | M37: =M32+M34-M36 -> -23.725
B38: =SCF!B38 -> Accounts Payable | C38: =SCF!C38 -> 6.25 | D38: =SCF!D38 -> 15 | E38: =SCF!E38 -> 31.25 | F38: =SCF!F38 -> 32.5 | H38: Total Asset Turnover (TATO) | I38: Times | J38: =C3/C35 -> 0.8 | K38: =D3/D35 -> 0.85714286 | L38: =E3/E35 -> 1 | M38: =F3/F35 -> 1.1111111
B39: =SCF!B39 -> Notes Payable | C39: =SCF!C39 -> 3.75 | D39: =SCF!D39 -> 16.25 | E39: =SCF!E39 -> 10 | F39: =SCF!F39 -> 22.5 | H39: Capital Intensity | I39: Times | J39: =C35/C3 -> 1.25 | K39: =D35/D3 -> 1.1666667 | L39: =E35/E3 -> 1 | M39: =F35/F3 -> 0.9
B40: =SCF!B40 -> Current Portion of LTD | C40: =SCF!C40 -> 5 | D40: =SCF!D40 -> 5 | E40: =SCF!E40 -> 5 | F40: =SCF!F40 -> 5 | H40: Fixed Asset Turnover | I40: Times | J40: =C3/C33 -> 1.1428571 | K40: =D3/D33 -> 1.4457831 | L40: =E3/E33 -> 1.6842105 | M40: =F3/F33 -> 1.8867925
B41: =SCF!B41 -> Total Current Liabilities | C41: =SUM(C38:C40) -> 15 | D41: =SUM(D38:D40) -> 36.25 | E41: =SUM(E38:E40) -> 46.25 | F41: =SUM(F38:F40) -> 60 | H41: NWC Turnover | I41: Times | J41: =C3/J7 -> 13.333333 | K41: =D3/K7 -> -120 | L41: =E3/L7 -> -17.777778 | M41: =F3/M7 -> -9.0909091
B43: =SCF!B43 -> Long Term Liabilities | H43: Market Value Measures
B44: =SCF!B44 -> Long Term Loan | C44: =SCF!C44 -> 25 | D44: =SCF!D44 -> 20 | E44: =SCF!E44 -> 15 | F44: =SCF!F44 -> 10 | H44: Earnings Per Share (EPS) | I44: $/Share | J44: =C12/C16 -> 0.07 | K44: =D12/D16 -> 0.35 | L44: =E12/E16 -> 0.63 | M44: =F12/F16 -> 0.245
B45: =SCF!B45 -> Bonds Payable | C45: =SCF!C45 -> 7.5 | D45: =SCF!D45 -> 10 | E45: =SCF!E45 -> 10 | F45: =SCF!F45 -> 10 | H45: Dividends Per Share (DPS) | I45: $/Share | J45: =C13/C16 -> 0.05 | K45: =D13/D16 -> 0.2 | L45: =E13/E16 -> 0.33 | M45: =F13/F16 -> 0.195
B46: =SCF!B46 -> Total Long Term Liabilities | C46: =SUM(C44:C45) -> 32.5 | D46: =SUM(D44:D45) -> 30 | E46: =SUM(E44:E45) -> 25 | F46: =SUM(F44:F45) -> 20 | H46: Price Earnings (PE) Ratio | I46: Times | J46: =C17/J44 -> 71.428571 | K46: =D17/K44 -> 21.428571 | L46: =E17/L44 -> 13.888889 | M46: =F17/M44 -> 25.510204
H47: Dividend Payout Ratio (DPO) | I47: % | J47: =C13/C12 -> 0.71428571 | K47: =D13/D12 -> 0.57142857 | L47: =E13/E12 -> 0.52380952 | M47: =F13/F12 -> 0.79591837
B48: =SCF!B48 -> Shareholders' Equity | H48: Dividend Yield | I48: % | J48: =J45/C17 -> 0.01 | K48: =K45/D17 -> 0.026666667 | L48: =L45/E17 -> 0.037714286 | M48: =M45/F17 -> 0.0312
B49: =SCF!B49 -> Contributed Capital | C49: =SCF!C49 -> 10 | D49: =SCF!D49 -> 12.5 | E49: =SCF!E49 -> 12.5 | F49: =SCF!F49 -> 15 | H49: Retention Ratio (RR) | I49: % | J49: =C14/C12 -> 0.28571429 | K49: =D14/D12 -> 0.42857143 | L49: =E14/E12 -> 0.47619048 | M49: =F14/F12 -> 0.20408163
B50: =SCF!B50 -> Retained Earnings | C50: =SCF!C50 -> 5 | D50: =C50+D14 -> 8.75 | E50: =D50+E14 -> 16.25 | F50: =E50+F14 -> 17.5 | H50: Market-to-Book Ratio | I50: Times | J50: =C17/(C51/C16) -> 8.3333333 | K50: =D17/(D51/D16) -> 8.8235294 | L50: =E17/(E51/E16) -> 7.6086957 | M50: =F17/(F51/F16) -> 4.8076923
B51: =SCF!B51 -> Total Shareholders' Equity | C51: =SUM(C49:C50) -> 15 | D51: =SUM(D49:D50) -> 21.25 | E51: =SUM(E49:E50) -> 28.75 | F51: =SUM(F49:F50) -> 32.5 | H51: Sustainable Growth Rate (g) | I51: % | J51: =J16*J49 -> 0.033333333 | K51: =K16*K49 -> 0.17647059 | L51: =L16*L49 -> 0.26086957 | M51: =M16*M49 -> 0.038461538
B53: =SCF!B53 -> Total Liabilities and Equity | C53: =C41+C46+C51 -> 62.5 | D53: =D41+D46+D51 -> 87.5 | E53: =E41+E46+E51 -> 100 | F53: =F41+F46+F51 -> 112.5 | H53: Differentiate between flow account and stock account in ratio calculatios!
B55: =SCF!B55 -> Balance | C55: =C35-C53 -> 0 | D55: =D35-D53 -> 0 | E55: =E35-E53 -> 0 | F55: =F35-F53 -> 0

Sheet CapitalBudgeting
A1: Year | B1: 0 | C1: =B1+1 -> 1 | D1: 2 | E1: 3 | F1: 4 | G1: 5 | I1: WACC | J1: 0.15 | L1: Delta Limited is planning on investing in a new project. This will involve the purchase of some new machinery costing $150 thousands that will be fully depreciated over 5 years. The salvage value is $30 thousands at the end of year 5. Delta Limited expects to receive cash flows of $40 thousands at the end of year 1, $50 thousands at the end of year 2, $60 thousands at the end of year 3, $70 thousands at the end of year 4, and $80 thousands at the end of year 5. Delta Limited expects to receive net income of $3 thousands at the end of year 1, $5 thousands at the end of year 2, $7 thousands at the end of year 3, $9 thousands at the end of year 4, and $11 thousands at the end of year 5. The weighted average cost of capital is 15%.
A2: FCF | B2: -150000 | C2: 40000 | D2: =C2+10000 -> 50000 | E2: =D2+10000 -> 60000 | F2: =E2+10000 -> 70000 | G2: =F2+10000 -> 80000 | I2: NPV | J2: =NPV(J1,C2:G2)+B2 -> 41837.632
A3: NI | C3: 3000 | D3: =C3+2000 -> 5000 | E3: =D3+2000 -> 7000 | F3: =E3+2000 -> 9000 | G3: =F3+2000 -> 11000 | I3: IRR | J3: =IRR(B2:G2) -> 0.2488685
A4: SV | B4: 30000 | I4: MIRR | J4: =MIRR(B2:G2,J1,J1) -> 0.20799837
I5: PI | J5: =(J2-B2)/(-B2) -> 1.2789175
A6: Year | B6: =B1 -> 0 | C6: =C1 -> 1 | D6: =D1 -> 2 | E6: =E1 -> 3 | F6: =F1 -> 4 | G6: =G1 -> 5 | I6: PBP | J6: =PERCENTRANK(B8:G8,0,6)*G6 -> 3 | K6: years
A7: FCF | B7: =B2 -> -150000 | C7: =C2 -> 40000 | D7: =D2 -> 50000 | E7: =E2 -> 60000 | F7: =F2 -> 70000 | G7: =G2 -> 80000 | I7: DPBP | J7: =PERCENTRANK(B13:G13,0,6)*G10 -> 3.94844 | K7: years | L7: 1. Calculate net present value (NPV) for this project.
A8: CFCF | B8: =B7 -> -150000 | C8: =B8+C7 -> -110000 | D8: =C8+D7 -> -60000 | E8: =D8+E7 -> 0 | F8: =E8+F7 -> 70000 | G8: =F8+G7 -> 150000 | I8: ARR | J8: =AVERAGE(C3:G3)/((-B2+B4)/2) -> 0.077777778 | L8: 2. Calculate internal rate of return (IRR) for this project.
A9: PBP | L9: 3. Calculate modified internal rate of return (MIRR) for this project.
A10: Year | B10: =B1 -> 0 | C10: =C1 -> 1 | D10: =D1 -> 2 | E10: =E1 -> 3 | F10: =F1 -> 4 | G10: =G1 -> 5 | L10: 4. Calculate profitability index (PI) for this project.
A11: FCF | B11: =B2 -> -150000 | C11: =C2 -> 40000 | D11: =D2 -> 50000 | E11: =E2 -> 60000 | F11: =F2 -> 70000 | G11: =G2 -> 80000 | L11: 5. Calculate payback period (PBP) for this project.
A12: DFCF | B12: =B11 -> -150000 | C12: =-PV($J$1,C10,,C11,0) -> 34782.609 | D12: =-PV($J$1,D10,,D11,0) -> 37807.183 | E12: =-PV($J$1,E10,,E11,0) -> 39450.974 | F12: =-PV($J$1,F10,,F11,0) -> 40022.727 | G12: =-PV($J$1,G10,,G11,0) -> 39774.139 | L12: 6. Calculate discounted payback period (DPBP) for this project.
A13: CDFCF | B13: =B12 -> -150000 | C13: =B13+C12 -> -115217.39 | D13: =C13+D12 -> -77410.208 | E13: =D13+E12 -> -37959.234 | F13: =E13+F12 -> 2063.4932 | G13: =F13+G12 -> 41837.632 | L13: 7. Calculate accounting rate of return (ARR) for this project.
A14: DPBP

Sheet CI-PV
A1: FV | B1: 40000 | D1: David would like to have a savings of $40,000 in an account at the end of five years. Calculate the amount he needs to save now if the savings account earns an annually effective rate of return of 8%.
A2: n | B2: 5
A3: i | B3: 0.08
A4: PV | B4: =-PV(B3,B2,,B1,0) -> 27223.328
D7: Use Excel built-in function!

Sheet CI-i
A1: PV | B1: 20000 | D1: Jennifer borrowed $20,000 from her best friend, four years later, Jennifer repaid her $26,000. Calculate the effective annual interest rate.
A2: n | B2: 4
A3: FV | B3: 26000
A4: i | B4: =RATE(B2,,-B1,B3,0) -> 0.067789972
D7: Use Excel built-in function!

Sheet CI-n
A1: PV | B1: 30000 | D1: Edward invested $30,000 in a fund offering a rate of return of 4% per year, approximately how many years will it take for the investment to reach $60,000?
A2: i | B2: 0.04
A3: FV | B3: 60000
A4: n | B4: =NPER(B2,,-B1,B3,0) -> 17.672988 | C4: years
D7: Use Excel built-in function!

Sheet FVOA-FV
A1: C | B1: 26000
A2: i | B2: 0.05
A3: n | B3: 3
A4: FV | B4: =FV(B2, B3, -B1, 0) -> 81965
I5: George will receive a study excellence award of $26,000 per year for the next 3 years. The effective annual interest rate is 5%. Calculate the future value of George's cash flows at the end of year 3.
D7: Use Excel built-in function!

Sheet FVOA-C
A1: FV | B1: 34000 | D1: Andrew would like to accumulate $34,000 in his savings account at the end of 5 years. If effective annual interest rate is 10%. What would be the amount of equal deposit at the end of each year for 5 years.
A2: i | B2: 0.1
A3: n | B3: 5
A4: C | B4: =PMT(B2, B3, , -B1, 0) -> 5569.1143
D7: Use Excel built-in function!
A9: rate | B9: 0.1
A10: c
A11: n | B11: 5
A12: PV | B12: 0

Sheet FVOA-i
A1: FV | B1: 30000 | D1: Kate deposits $6,000 at the end of each year for 4 years that resulted in an accumulated value of $30,000 at the end of year 4. Calculate the effective annual interest rate.
A2: C | B2: 6000
A3: n | B3: 4
A4: i | B4: =RATE(B3, -B2, 0, B1, 0) -> 0.15091108
D7: Use Excel built-in function!

Sheet FVOA-n
A1: C | B1: 4300 | D1: Kate deposits $4,300 at the end of each year at 8% annual effective interest rate that accumulated a future value of $20,000. How long does it take to accumulate this future value?
A2: FV | B2: 20000
A3: i | B3: 0.08
A4: n | B4: =NPER(B3, B1,, -B2, 0) -> 4.1103567 | H4: year 0 | I4: year 1 | J4: year 2 | K4: year 3 | L4: year 4 | M4: year 5 | N4: year 6 | O4: year 7
H5: 0 | I5: 4300 | J5: =4300+(I5*1.08) -> 8944 | K5: =4300+(J5*1.08) -> 13959.52 | L5: =4300+(K5*1.08) -> 19376.282 | M5: =4300+(L5*1.08) -> 25226.384 | N5: =4300+(M5*1.08) -> 31544.495 | O5: =4300+(N5*1.08) -> 38368.054
I6: 1.08
D7: Use Excel built-in function! | L7: =4644+(4300*1.08) -> 9288

Sheet PVOA-PV
A1: C | B1: 33000 | D1: George will receive a study excellence award of $33,000 per year for the next 3 years. The effective annual interest rate is 12%. Calculate the present value today of George's cash flows.
A2: i | B2: 0.12
A3: n | B3: 3
A4: PV | B4: =PV(12%,3,-33000) -> 79260.432
D7: Use Excel built-in function!

Sheet PVOA-C
A1: PV | B1: 60000 | D1: Jacqueline deposited $0,000 at 9% effective annual interest rate. She will make equal withdrawals at the end of each year over a 6-year term. What would be the amount of equal withdrawal?
A2: i | B2: 0.09
A3: n | B3: 6
A4: C | B4: =PMT(9%,6,-60000) -> 13375.187
D7: Use Excel built-in function!

Sheet PVOA-i
A1: PV | B1: 30000 | D1: Sam got a $30,000 loan and repays instalments of $12,000 at the end of each year for 3 years. Calculate the effective annual interest rate.
A2: C | B2: 12000
A3: n | B3: 3
A4: i | B4: =RATE(3,12000,-30000) -> 0.097010257
D7: Use Excel built-in function!

Sheet PVOA-n
A1: C | B1: 11000 | D1: Samantha got a loan of $110,000 at 5% annual effective interest rate. She repays annual instalments of $11,000 at the end of each year. How long does it take to repay the loan?
A2: PV | B2: 110000
A3: i | B3: 0.05
A4: n | B4: =NPER(5%, -11000,0, 110000) -> 8.3103862
D7: Use Excel built-in function!

Sheet R&R Sample
A1: Year | B1: Annual Return | D1: Delta Limited share has the following annual returns for the given years respectively.
A2: 2016 | B2: 0.12
A3: =A2+1 -> 2017 | B3: 0.08
A4: =A3+1 -> 2018 | B4: 0
A5: =A4+1 -> 2019 | B5: 0.04
D6: Use Excel built-in function!
A7: Risk Free Rate | B7: 0.01
A9: Average Return | B9: =AVERAGE(B2:B5) -> 0.06 | D9: 1. Calculate average yearly return?
A10: Variance | B10: =VAR(B2:B5) -> 0.0026666667 | D10: 2. Calculate variance?
A11: Volatility | B11: =SQRT(B10) -> 0.051639778 | D11: 3. Calculate volatility?
A12: Coefficient of Variation | B12: =B11/B9 -> 0.86066297 | D12: 4. Calculate coefficient of variation
A13: Sharpe Ratio | B13: =B9-B7/B11 -> -0.13364917 | D13: 5. Calculate Sharpe ratio if risk free rate is 1%.
D15: Use Excel built-in function for parts a, b, and c!
A16: or variance

Sheet R&R Probability
A1: State | B1: Probability | C1: Return | E1: An investor believes that the returns for an investment depends on the state of the economy. The following data are provided regarding each state and return.
A2: Growth | B2: 0.05 | C2: 0.1
A3: Stable | B3: 0.5 | C3: 0.06
A4: Recession | B4: =1-SUM(B2:B3) -> 0.45 | C4: -0.02
A7: Risk Free Rate | B7: 0.01
A9: Expected Return | B9: =(B2*C2)+(B3*C3)+(B4*C4) -> 0.026 | E9: 1. Calculate expected return?
A10: Variance | B10: =B2*(C2-B9)^2+B3*(C3-B9)^2+B4*(C4-B9)^2 -> 0.001804 | E10: 2. Calculate variance?
A11: Volatility | B11: =SQRT(B10) -> 0.042473521 | E11: 3. Calculate volatility?
A12: Coefficient of Variation | B12: =B11/B9 -> 1.633597 | E12: 4. Calculate coefficient of variation
A13: Sharpe Ratio | B13: =B9-B7/B11 -> -0.2094408 | E13: 5. Calculate Sharpe ratio if risk free rate is 1%.

Sheet R&R Portfolio
A1: Share | B1: Investment | C1: Weight | D1: E(R) | E1: STD | F1: Beta | H1: An investor holds a portfolio of two shares. The correlation between the two shares is 0.80 and their expected return, volatility and beta as follows:
A2: A | B2: 270000 | C2: =B2/B4 -> 0.75 | D2: 0.12 | E2: 0.16 | F2: 1.4
A3: B | B3: 90000 | C3: =B3/B4 -> 0.25 | D3: 0.08 | E3: 0.12 | F3: 1.2
A4: Total | B4: =SUM(B2:B3) -> 360000 | C4: =SUM(C2:C3) -> 1
A6: Correlation | B6: 0.8
A7: Risk Free Rate | B7: 0.01
A9: Expected Return | B9: =(C2*D2)+(C3*D3) -> 0.11 | H9: 1. Calculate portfolio expected return?
A10: Variance | B10: =C2^2*E2^2+C3^2*E3^2+2*B6*C2*C3*E2*E3 -> 0.02106 | H10: 2. Calculate portfolio variance?
A11: Volatility | B11: =SQRT(B10) -> 0.14512064 | H11: 3. Calculate portfolio volatility?
A12: Coefficient of Variation | B12: =B11/B9 -> 1.3192785 | H12: 4. Calculate portfolio coefficient of variation
A13: Sharpe Ratio | B13: =B9-B7/B11 -> 0.041091814 | H13: 5. Calculate portfolio Sharpe ratio if risk free rate is 1%.
A14: Expected Beta | B14: =(C2*F2)+(C3*F3) -> 1.35 | H14: 6. Calculate portfolio beta.

Sheet Risk Mgmt Long
A1: Contract Type | B1: Forward | E1: Delta Limited, a gold manufacturer, goes long in a forward contract with an exercise price of $700 per ounce for 5,000 ounces only to be exercised in 6 months. Calculate the gain or loss in the following cases:
A2: Position | B2: Long
A3: Exercise Price | B3: 700
A4: Quantity | B4: 5000
B6: Scenario 1 | C6: Scenario 2
A7: Market Price | B7: =B3+200 -> 900 | C7: =B3-300 -> 400 | E7: 1. If market gold price after 6 months is $900 per ounce.
A8: Gain/Loss | B8: =(B7-B3)*B4 -> 1000000 | C8: =(C7-B3)*B4 -> -1500000 | E8: 2. If market gold price after 6 months is $400 per ounce.
B9: Scenario 1 = Gain | C9: Scenario 2 = Loss

Sheet Risk Mgmt Short
A1: Contract Type | B1: Forward | E1: Delta Limited, a gold producer, goes short in a forward contract with an exercise price of $700 per ounce for 5,000 ounces only to be exercised in 6 months. Calculate the gain or loss in the following cases:
A2: Position | B2: Short
A3: Exercise Price | B3: ='Risk Mgmt Long'!B3 -> 700
A4: Quantity | B4: ='Risk Mgmt Long'!B4 -> 5000
B6: Scenario 1 | C6: Scenario 2
A7: Market Price | B7: ='Risk Mgmt Long'!B7 -> 900 | C7: ='Risk Mgmt Long'!C7 -> 400 | E7: ='Risk Mgmt Long'!E7 -> 1. If market gold price after 6 months is $900 per ounce.
A8: Gain/Loss | B8: =(B3-B7)*B4 -> -1000000 | C8: =(B3-C7)*B4 -> 1500000 | E8: ='Risk Mgmt Long'!E8 -> 2. If market gold price after 6 months is $400 per ounce.
B9: Scenario 1 = Loss | C9: Scenario 2 = Gain

Sheet M&A Cash
B1: Acquirer | C1: Target | D1: Amount | G1: Cash | H1: Scrip | J1: Pioneer Limited plans to acquire Delta Limited. Pioneer Limited plans to propose a cash offer by paying the market price of Delta’s shares as well as paying 60% of synergy created in the market value of assets. This deal expects to generate synergy of additional $200,000 of market value of assets and $40,000 of net income. Assume there is no transaction cost, financial and operating risk remain constant. Use the following financial data of both Pioneer Limited and Delta Limited to estimate the following:
A2: Synergy | B2: =100%-C2 -> 0.4 | C2: 0.6 | F2: Offer | G2: 1
A3: MVA | D3: 200000
A4: NI | D4: 40000
B5: Pioneer Limited | C5: Delta Limited | D5: =B5 -> Pioneer Limited
D6: After Acquistion
A7: Share Price | B7: 20 | C7: 12 | D7: =D11/D8 -> 16
A8: Shares Outstanding | B8: 25000 | C8: 10000 | D8: =B8 -> 25000
A9: MVA | B9: 1400000 | C9: 300000 | D9: =B9+C9+D3-(C9+D3*C2) -> 1480000 | J9: 1. Calculated market value of equity of Pioneer Limited and Delta Limited.
A10: Net Income | B10: 150000 | C10: 75000 | D10: =B10+C10+D4 -> 265000 | J10: 2. Calculated market value of debt of Pioneer Limited and Delta Limited.
A11: MVE | B11: =B7*B8 -> 500000 | C11: =C7*C8 -> 120000 | D11: =D9-D12 -> 400000 | J11: 3. Calculated debt-to-equity ratio of Pioneer Limited and Delta Limited.
A12: MVD | B12: =B9-B11 -> 900000 | C12: =C9-C11 -> 180000 | D12: =B12+C12 -> 1080000 | J12: 4. Calculated earnings per share ratio of Pioneer Limited and Delta Limited.
A13: D/E | B13: =B12/B11 -> 1.8 | C13: =C12/C11 -> 1.5 | D13: =D12/D11 -> 2.7 | J13: 5. Calculated price-earnings ratio of Pioneer Limited and Delta Limited.
A14: EPS | B14: =B10/B8 -> 6 | C14: =C10/C8 -> 7.5 | D14: =D10/D8 -> 10.6 | J14: 6. Calculated market value of assets of Pioneer Limited after acquisition.
A15: PE | B15: =B7/B14 -> 3.3333333 | C15: =C7/C14 -> 1.6 | D15: =D7/D14 -> 1.509434 | J15: 7. Calculated market value of debt of Pioneer Limited after acquisition.
J16: 8. Calculated market value of equity of Pioneer Limited after acquisition.
J17: 9. Calculated net income of Pioneer Limited after acquisition.
J18: 10. Calculated shares outstanding of Pioneer Limited after acquisition.
J19: 11. Calculated share price of Pioneer Limited after acquisition.
J20: 12. Calculated debt-to-equity ratio of Pioneer Limited after acquisition.
J21: 13. Calculated earnings per share ratio of Pioneer Limited after acquisition.
J22: 14. Calculated price-earnings ratio of Pioneer Limited after acquisition.

Sheet M&A Scrip
B1: Acquirer | C1: Target | D1: Amount | G1: Cash | H1: Scrip | J1: Pioneer Limited plans to acquire Delta Limited. Pioneer Limited plans to propose a scrip offer by paying the market price of Delta’s shares as well as paying 60% of synergy created in the market value of assets. This deal expects to generate synergy of additional $200,000 of market value of assets and $40,000 of net income. Assume there is no transaction cost, financial and operating risk remain constant. Use the following financial data of both Pioneer Limited and Delta Limited to estimate the following:
A2: Synergy | B2: =100%-C2 -> 0.4 | C2: ='M&A Cash'!C2 -> 0.6 | F2: Offer | G2: =100%-H2 -> 0.2 | H2: 0.8
A3: MVA | D3: ='M&A Cash'!D3 -> 200000
A4: NI | D4: ='M&A Cash'!D4 -> 40000
B5: ='M&A Cash'!B5:B6 -> Pioneer Limited | C5: ='M&A Cash'!C5:C6 -> Delta Limited | D5: =B5 -> Pioneer Limited | E5: Pioneer* | F5: Delta*
D6: After Acquistion
A7: Share Price | B7: ='M&A Cash'!B7 -> 20 | C7: ='M&A Cash'!C7 -> 12 | D7: =D11/D8 -> 32.8 | E7: =D7 -> 32.8 | F7: =E7 -> 32.8
A8: Shares Outstanding | B8: ='M&A Cash'!B8 -> 25000 | C8: ='M&A Cash'!C8 -> 10000 | D8: =B8 -> 25000 | E8: =B8 -> 25000 | F8: =C11/D7 -> 3658.5366
A9: MVA | B9: ='M&A Cash'!B9 -> 1400000 | C9: ='M&A Cash'!C9 -> 300000 | D9: =B9+C9+D3 -> 1900000 | J9: 1. Calculated market value of equity of Pioneer Limited and Delta Limited.
A10: Net Income | B10: ='M&A Cash'!B10 -> 150000 | C10: ='M&A Cash'!C10 -> 75000 | D10: =B10+C10+D4 -> 265000 | J10: 2. Calculated market value of debt of Pioneer Limited and Delta Limited.
A11: MVE | B11: =B7*B8 -> 500000 | C11: =C7*C8 -> 120000 | D11: =D9-D12 -> 820000 | E11: =B11+D3*B2 -> 580000 | F11: =C11+D3*C2 -> 240000 | J11: 3. Calculated debt-to-equity ratio of Pioneer Limited and Delta Limited.
A12: MVD | B12: =B9-B11 -> 900000 | C12: =C9-C11 -> 180000 | D12: =B12+C12 -> 1080000 | J12: 4. Calculated earnings per share ratio of Pioneer Limited and Delta Limited.
A13: D/E | B13: =B12/B11 -> 1.8 | C13: =C12/C11 -> 1.5 | D13: =D12/D11 -> 1.3170732 | J13: 5. Calculated price-earnings ratio of Pioneer Limited and Delta Limited.
A14: EPS | B14: =B10/B8 -> 6 | C14: =C10/C8 -> 7.5 | D14: =D10/D8 -> 10.6 | J14: 6. Calculated market value of assets of Pioneer Limited after acquisition.
A15: PE | B15: =B7/B14 -> 3.3333333 | C15: =C7/C14 -> 1.6 | D15: =D7/D14 -> 3.0943396 | J15: 7. Calculated market value of debt of Pioneer Limited after acquisition.
J16: 8. Calculated market value of equity of Pioneer Limited after acquisition, market value of equity for both acquirer and target after acquisition.
J17: 9. Calculated net income of Pioneer Limited after acquisition.
J18: 10. Calculated shares outstanding of Pioneer Limited after acquisition.
J19: 11. Calculated shares outstanding of Pioneer Limited after acquisition and shares offered to the target firm.
J20: 12. Calculated debt-to-equity ratio of Pioneer Limited after acquisition.
J21: 13. Calculated earnings per share ratio of Pioneer Limited after acquisition.
J22: 14. Calculated price-earnings ratio of Pioneer Limited after acquisition.

Sheet M&A Combined
B1: Acquirer | C1: Target | D1: Amount | G1: Cash | H1: Scrip | J1: Pioneer Limited plans to acquire Delta Limited. Pioneer Limited plans to propose a 80% scrip offer by paying the market price of Delta’s shares as well as paying 60% of synergy created in the market value of assets. This deal expects to generate synergy of additional $200,000 of market value of assets and $40,000 of net income. Assume there is no transaction cost, financial and operating risk remain constant. Use the following financial data of both Pioneer Limited and Delta Limited to estimate the following:
A2: Synergy | B2: =100%-C2 -> 0.4 | C2: ='M&A Cash'!C2 -> 0.6 | F2: Offer | G2: =100%-H2 -> 0.2 | H2: 0.8
A3: MVA | D3: ='M&A Cash'!D3 -> 200000
A4: NI | D4: ='M&A Cash'!D4 -> 40000
B5: ='M&A Cash'!B5:B6 -> Pioneer Limited | C5: ='M&A Cash'!C5:C6 -> Delta Limited | D5: =B5 -> Pioneer Limited | E5: ='M&A Scrip'!E5:E6 -> Pioneer* | F5: ='M&A Scrip'!F5:F6 -> Delta*
D6: After Acquistion
A7: Share Price | B7: ='M&A Cash'!B7 -> 20 | C7: ='M&A Cash'!C7 -> 12 | D7: =E11/B8 -> 15.52 | E7: =E11/B8 -> 15.52 | F7: =F11/C8 -> 24
A8: Shares Outstanding | B8: ='M&A Cash'!B8 -> 25000 | C8: ='M&A Cash'!C8 -> 10000 | D8: =F8+E8 -> 40463.918 | E8: =B8 -> 25000 | F8: =F11/D7 -> 15463.918
A9: MVA | B9: ='M&A Cash'!B9 -> 1400000 | C9: ='M&A Cash'!C9 -> 300000 | D9: =B9+C9+D3-(H2*(C11+C2*D3)) -> 1708000 | J9: 1. Calculated market value of equity of Pioneer Limited and Delta Limited.
A10: Net Income | B10: ='M&A Cash'!B10 -> 150000 | C10: ='M&A Cash'!C10 -> 75000 | D10: =B10+C10+D4 -> 265000 | J10: 2. Calculated market value of debt of Pioneer Limited and Delta Limited.
A11: MVE | B11: =B7*B8 -> 500000 | C11: =C7*C8 -> 120000 | D11: =D9-D12 -> 628000 | E11: =D11-F11 -> 388000 | F11: =(D3*C2)+C11 -> 240000 | J11: 3. Calculated debt-to-equity ratio of Pioneer Limited and Delta Limited.
A12: MVD | B12: =B9-B11 -> 900000 | C12: =C9-C11 -> 180000 | D12: =B12+C12 -> 1080000 | J12: 4. Calculated earnings per share ratio of Pioneer Limited and Delta Limited.
A13: D/E | B13: =B12/B11 -> 1.8 | C13: =C12/C11 -> 1.5 | D13: =D12/D11 -> 1.7197452 | J13: 5. Calculated price-earnings ratio of Pioneer Limited and Delta Limited.
A14: EPS | B14: =B10/B8 -> 6 | C14: =C10/C8 -> 7.5 | D14: =D10/D8 -> 6.5490446 | J14: 6. Calculated market value of assets of Pioneer Limited after acquisition.
A15: PE | B15: =B7/B14 -> 3.3333333 | C15: =C7/C14 -> 1.6 | D15: =D7/D14 -> 2.3698113 | J15: 7. Calculated market value of debt of Pioneer Limited after acquisition.
J16: 8. Calculated market value of equity of Pioneer Limited after acquisition, market value of equity for both acquirer and target after acquisition.
J17: 9. Calculated net income of Pioneer Limited after acquisition.
J18: 10. Calculated shares outstanding of Pioneer Limited after acquisition.
J19: 11. Calculated shares outstanding of Pioneer Limited after acquisition and shares offered to the target firm.
J20: 12. Calculated debt-to-equity ratio of Pioneer Limited after acquisition.
J21: 13. Calculated earnings per share ratio of Pioneer Limited after acquisition.
J22: 14. Calculated price-earnings ratio of Pioneer Limited after acquisition.

Sheet Outsourcing 1
A1: Current demand | B1: 450000 | E1: You have the following information for insourcing (Pioneer Limited) and the outsourcing (Delta Limited). If the current demand is 450,000 shall outsourcing or insourcing used?
B4: Insourcing | C4: Outsourcing
B5: Pioneer Limited | C5: Delta Limited
A6: Fixed cost | B6: 12000000 | C6: 10000000
A7: Variable cost/unit | B7: 30 | C7: 35
A10: Break-even point | B10: =(B6-C6)/(C7-B7) -> 400000
A11: Decision | B11: =IF(B1>B10,"insource", "outsource") -> insource

Sheet Outsourcing 2
B1: Outsourcing Providers | G1: You would like to rate outsourcing providers. Your team developed seven factors rated 1-5, and an importance weight is given to each factor. Your team applied the seven factors to the three outsourcing providers. Which outsourcing providers shall you choose?
A2: Factor (criterion) | B2: Importance Weight | C2: Pioneer Limited | D2: Sigma Limited | E2: Venus Limited
A3: 1. Can reduce operating costs | B3: 0.15 | C3: 5 | D3: 3 | E3: 1
A4: 2. Can reduce capital investment | B4: 0.15 | C4: 1 | D4: 1 | E4: 2
A5: 3. Skilled personnel | B5: 0.15 | C5: 1 | D5: 4 | E5: 5
A6: 4. Can improve quality | B6: 0.15 | C6: 5 | D6: 1 | E6: 2
A7: 5. Can gain access to technology not in company | B7: 0.15 | C7: 5 | D7: 2 | E7: 4
A8: 6. Can create additional capacity | B8: 0.1 | C8: 1 | D8: 1 | E8: 3
A9: 7. Aligns with policy/ philosophy/culture | B9: 0.15 | C9: 5 | D9: 4 | E9: 3
A10: Total and Weighted Averages | B10: 1 | C10: =SUMPRODUCT($B$3:$B$9,C3:C9) -> 3.4 | D10: =SUMPRODUCT($B$3:$B$9,D3:D9) -> 2.35 | E10: =SUMPRODUCT($B$3:$B$9,E3:E9) -> 2.85
A13: Criteria | B13: =MAX(C10:E10) -> 3.4
A14: Decision | B14: =_xlfn.XLOOKUP(B13,C10:E10,C2:E2) -> Pioneer Limited

Sheet Outsourcing 3
A1: Risk Factor | B1: Brazil | C1: Columbia | D1: Phillipenne | F1: You would like to rate outsourcing providers using rating international risk factors. Your team developed nine risk factors rated 0-3 (0 is no risk, and 3 is high risk). Your team applied the nine factors to the countries of the three outsourcing providers. Which country shall you choose?
A2: Economic: Labor cost/ laws | B2: 0 | C2: 1 | D2: 2
A3: Economic: Capital availability | B3: 0 | C3: 2 | D3: 3
A4: Economic: Infrastructure | B4: 3 | C4: 3 | D4: 0
A5: Culture: Language | B5: 1 | C5: 0 | D5: 0
A6: Culture: Social norms | B6: 2 | C6: 0 | D6: 2
A7: Migration: Uncontrolled | B7: 3 | C7: 3 | D7: 0
A8: Politics: Ideology | B8: 1 | C8: 0 | D8: 2
A9: Politics: Instability | B9: 2 | C9: 0 | D9: 0
A10: Politics: Legalities | B10: 2 | C10: 1 | D10: 2
A11: Total risk rating scores | B11: =SUM(B2:B10) -> 14 | C11: =SUM(C2:C10) -> 10 | D11: =SUM(D2:D10) -> 11
A13: Criteria | B13: =MIN(B11:D11) -> 10
A14: Decision | B14: =_xlfn.XLOOKUP(B13,B11:D11,B1:D1) -> Columbia

Sheet Sheet1
B2: Horizontal Analysis
C3: 2019 | D3: 2020 | E3: 2021 | F3: 2022 | J3: 2019 | K3: 2020 | L3: 2021 | M3: 2022
B4: Current Assets | I4: Total Current Assets | J4: 0 | K4: 0.9 | L4: 1.1666667 | M4: 1.4666667
B5: Cash | C5: 0 | D5: 1.5 | E5: 2 | F5: 3 | I5: Total Long Term Assets | J5: 0 | K5: 0.18571429 | L5: 0.35714286 | M5: 0.51428571
B6: Accounts Receivable | C6: 0 | D6: 1.3333333 | E6: 1.6666667 | F6: 2.6666667 | I6: Total Assets | J6: 0 | K6: 0.4 | L6: 0.6 | M6: 0.8
B7: Inventories | C7: 0 | D7: 0.5 | E7: 0.66666667 | F7: 0.33333333
B8: Other Current Assets | C8: 0 | D8: 2 | E8: 2.5 | F8: 5
B9: Total Current Assets | C9: 0 | D9: 0.9 | E9: 1.1666667 | F9: 1.4666667
B11: Long Term Assets
B12: PPE (Gross) | C12: 0 | D12: 0.16666667 | E12: 0.33333333 | F12: 0.5
B13: Acc Dep | C13: 0 | D13: 0.11666667 | E13: 0.25 | F13: 0.4
B14: PPE (Net) | C14: 0 | D14: 0.21666667 | E14: 0.41666667 | F14: 0.6
B15: Goodwill | C15: 0 | D15: 0 | E15: 0 | F15: 0
B16: Total Long Term Assets | C16: 0 | D16: 0.18571429 | E16: 0.35714286 | F16: 0.51428571
J17: 2019 | K17: 2020 | L17: 2021 | M17: 2022
B18: Total Assets | C18: 0 | D18: 0.4 | E18: 0.6 | F18: 0.8 | K18: 1.4166667 | L18: 2.0833333 | M18: 3
J19: 0 | K19: -0.076923077 | L19: -0.23076923 | M19: -0.38461538
B20: Current Liabilities
B21: Accounts Payable | C21: 0 | D21: 1.4 | E21: 4 | F21: 4.2
B22: Notes Payable | C22: 0 | D22: 3.3333333 | E22: 1.6666667 | F22: 5 | J22: 2019 | K22: 2020 | L22: 2021 | M22: 2022
B23: Current Portion of LTD | C23: 0 | D23: 0 | E23: 0 | F23: 0 | I23: Total Liabilities | J23: =SUM(J18,J19) -> 0 | K23: =SUM(K18,K19) -> 1.3397436 | L23: =SUM(L18,L19) -> 1.8525641 | M23: =SUM(M18,M19) -> 2.6153846
B24: Total Current Liabilities | C24: 0 | D24: 1.4166667 | E24: 2.0833333 | F24: 3 | I24: Total Assets | J24: 0 | K24: 0.4 | L24: 0.6 | M24: 0.8
B26: Long Term Liabilities
B27: Long Term Loan | C27: 0 | D27: -0.2 | E27: -0.4 | F27: -0.6
B28: Bonds Payable | C28: 0 | D28: 0.33333333 | E28: 0.33333333 | F28: 0.33333333
B29: Total Long Term Liabilities | C29: 0 | D29: -0.076923077 | E29: -0.23076923 | F29: -0.38461538
B31: Shareholders' Equity
B32: Contributed Capital | C32: 0 | D32: 0.25 | E32: 0.25 | F32: 0.5
B33: Retained Earnings | C33: 0 | D33: 0.75 | E33: 2.25 | F33: 2.5
B34: Total Shareholders' Equity | C34: 0 | D34: 0.41666667 | E34: 0.91666667 | F34: 1.1666667
B36: Total Liabilities and Equity | C36: 0 | D36: 0.4 | E36: 0.6 | F36: 0.8
